[
    {
        "target_id": 1465748192864129035,
        "target_screen_name": "KevinEducates",
        "source_id": 1351202858629263361
    },
    {
        "target_id": 1384903427625476100,
        "target_screen_name": "CrimsonGradient",
        "source_id": 1351202858629263361
    },
    {
        "target_id": 1105083277742931968,
        "target_screen_name": "loehrgui",
        "source_id": 1351202858629263361
    },
    {
        "target_id": 300438906,
        "target_screen_name": "TommyLofstedt",
        "source_id": 1351202858629263361
    },
    {
        "target_id": 1108609164,
        "target_screen_name": "JessedePagter",
        "source_id": 1351202858629263361
    },
    {
        "target_id": 1345080072,
        "target_screen_name": "erencoder",
        "source_id": 1351202858629263361
    },
    {
        "target_id": 454777154,
        "target_screen_name": "carolinabranby",
        "source_id": 1351202858629263361
    },
    {
        "target_id": 1240190339379605504,
        "target_screen_name": "ai4mediaproject",
        "source_id": 1351202858629263361
    },
    {
        "target_id": 507171003,
        "target_screen_name": "ades_tweets",
        "source_id": 1351202858629263361
    },
    {
        "target_id": 1689597571,
        "target_screen_name": "ClaudiaWQ",
        "source_id": 1351202858629263361
    },
    {
        "target_id": 924340896,
        "target_screen_name": "joaovalcordeiro",
        "source_id": 1351202858629263361
    },
    {
        "target_id": 16179703,
        "target_screen_name": "manuel_guerrero",
        "source_id": 1351202858629263361
    },
    {
        "target_id": 1011585253423665152,
        "target_screen_name": "MSlavkovik",
        "source_id": 1351202858629263361
    },
    {
        "target_id": 2228091020,
        "target_screen_name": "PAHanania",
        "source_id": 1351202858629263361
    },
    {
        "target_id": 38628675,
        "target_screen_name": "ulisescortes",
        "source_id": 1351202858629263361
    },
    {
        "target_id": 1620752436,
        "target_screen_name": "obakiner",
        "source_id": 1351202858629263361
    },
    {
        "target_id": 4288099702,
        "target_screen_name": "robolegist",
        "source_id": 1351202858629263361
    },
    {
        "target_id": 190568491,
        "target_screen_name": "bilgesu_sumer",
        "source_id": 1351202858629263361
    },
    {
        "target_id": 1045748604,
        "target_screen_name": "amironesei",
        "source_id": 1351202858629263361
    },
    {
        "target_id": 1183874861489250304,
        "target_screen_name": "DavidAttenbird",
        "source_id": 1351202858629263361
    },
    {
        "target_id": 1102966738445049857,
        "target_screen_name": "JamesSteinhof17",
        "source_id": 1351202858629263361
    },
    {
        "target_id": 895778265100681216,
        "target_screen_name": "AdriBenben",
        "source_id": 1351202858629263361
    },
    {
        "target_id": 1093478004955713537,
        "target_screen_name": "l010101010101",
        "source_id": 1351202858629263361
    },
    {
        "target_id": 1453425200268206084,
        "target_screen_name": "HafizeCelik0616",
        "source_id": 1351202858629263361
    },
    {
        "target_id": 610323,
        "target_screen_name": "SergeStinckwich",
        "source_id": 1351202858629263361
    },
    {
        "target_id": 1351085258901508099,
        "target_screen_name": "AICCELERATE_eu",
        "source_id": 1351202858629263361
    },
    {
        "target_id": 76504000,
        "target_screen_name": "lesleywilton",
        "source_id": 1351202858629263361
    },
    {
        "target_id": 1230462329596321792,
        "target_screen_name": "taxtechkat",
        "source_id": 1351202858629263361
    },
    {
        "target_id": 1191281093191835648,
        "target_screen_name": "ricardovinuesa",
        "source_id": 1351202858629263361
    },
    {
        "target_id": 1097481442366492677,
        "target_screen_name": "ARTAIBath",
        "source_id": 1351202858629263361
    },
    {
        "target_id": 1345338183563804672,
        "target_screen_name": "KasiaS81084714",
        "source_id": 1351202858629263361
    },
    {
        "target_id": 1427913464610099202,
        "target_screen_name": "rmitciairi",
        "source_id": 1351202858629263361
    },
    {
        "target_id": 601327933,
        "target_screen_name": "medieonie",
        "source_id": 1351202858629263361
    },
    {
        "target_id": 69418536,
        "target_screen_name": "sergiohenryrico",
        "source_id": 1351202858629263361
    },
    {
        "target_id": 1416302576400797696,
        "target_screen_name": "ElinSporrong",
        "source_id": 1351202858629263361
    },
    {
        "target_id": 39600621,
        "target_screen_name": "SassanGholiagha",
        "source_id": 1351202858629263361
    },
    {
        "target_id": 2401807519,
        "target_screen_name": "simonfeck2",
        "source_id": 1351202858629263361
    },
    {
        "target_id": 506987932,
        "target_screen_name": "gabriellearuta",
        "source_id": 1351202858629263361
    },
    {
        "target_id": 284209788,
        "target_screen_name": "smnikpoor",
        "source_id": 1351202858629263361
    },
    {
        "target_id": 2195449950,
        "target_screen_name": "ashiquealit",
        "source_id": 1351202858629263361
    },
    {
        "target_id": 98031524,
        "target_screen_name": "sreddola",
        "source_id": 1351202858629263361
    },
    {
        "target_id": 19980293,
        "target_screen_name": "CreateSpark",
        "source_id": 1351202858629263361
    },
    {
        "target_id": 45587141,
        "target_screen_name": "parrasaiani",
        "source_id": 1351202858629263361
    },
    {
        "target_id": 1919987095,
        "target_screen_name": "IceLab_umea",
        "source_id": 1351202858629263361
    },
    {
        "target_id": 1200763760,
        "target_screen_name": "moaerikssonkrut",
        "source_id": 1351202858629263361
    },
    {
        "target_id": 1397997710641410050,
        "target_screen_name": "AlirezaTCS",
        "source_id": 1351202858629263361
    },
    {
        "target_id": 1336585537,
        "target_screen_name": "misicjane",
        "source_id": 1351202858629263361
    },
    {
        "target_id": 1435649742273384448,
        "target_screen_name": "lawnchem",
        "source_id": 1351202858629263361
    },
    {
        "target_id": 1360478372040642566,
        "target_screen_name": "NiteshRai_",
        "source_id": 1351202858629263361
    },
    {
        "target_id": 10833842,
        "target_screen_name": "mtenkoppel",
        "source_id": 1351202858629263361
    },
    {
        "target_id": 58579927,
        "target_screen_name": "TheBlueLu",
        "source_id": 1351202858629263361
    },
    {
        "target_id": 1277300765879685123,
        "target_screen_name": "MJPepaPlana",
        "source_id": 1351202858629263361
    },
    {
        "target_id": 1444588025665757184,
        "target_screen_name": "wallenberg_jr",
        "source_id": 1351202858629263361
    },
    {
        "target_id": 131603419,
        "target_screen_name": "aegansjo",
        "source_id": 1351202858629263361
    },
    {
        "target_id": 256677773,
        "target_screen_name": "TEFAOSAMA",
        "source_id": 1351202858629263361
    },
    {
        "target_id": 357450538,
        "target_screen_name": "richardblythman",
        "source_id": 1351202858629263361
    },
    {
        "target_id": 1704585566,
        "target_screen_name": "ChalmersICT",
        "source_id": 1351202858629263361
    },
    {
        "target_id": 1305878756356222977,
        "target_screen_name": "_sofiapalmieri",
        "source_id": 1351202858629263361
    },
    {
        "target_id": 1433028426,
        "target_screen_name": "atcortesm",
        "source_id": 1351202858629263361
    },
    {
        "target_id": 2904865133,
        "target_screen_name": "MCoeckelbergh",
        "source_id": 1351202858629263361
    },
    {
        "target_id": 20660144,
        "target_screen_name": "UmeaUniversity",
        "source_id": 1351202858629263361
    },
    {
        "target_id": 2147600012,
        "target_screen_name": "pettter_e",
        "source_id": 1351202858629263361
    },
    {
        "target_id": 1276618386559164421,
        "target_screen_name": "idilbriefss",
        "source_id": 1351202858629263361
    },
    {
        "target_id": 310844730,
        "target_screen_name": "tornqvistmax",
        "source_id": 1351202858629263361
    },
    {
        "target_id": 1441245676407455754,
        "target_screen_name": "GinaColeLive",
        "source_id": 1351202858629263361
    },
    {
        "target_id": 1370436729140830212,
        "target_screen_name": "in_responsible",
        "source_id": 1351202858629263361
    },
    {
        "target_id": 946139024,
        "target_screen_name": "CatMKennedy",
        "source_id": 1351202858629263361
    },
    {
        "target_id": 24060313,
        "target_screen_name": "ndconnell",
        "source_id": 1351202858629263361
    },
    {
        "target_id": 258788120,
        "target_screen_name": "alejandroarcej",
        "source_id": 1351202858629263361
    },
    {
        "target_id": 1430166515362451460,
        "target_screen_name": "TBTEvents1",
        "source_id": 1351202858629263361
    },
    {
        "target_id": 887618573102919680,
        "target_screen_name": "JohannesGeith",
        "source_id": 1351202858629263361
    },
    {
        "target_id": 1110501908,
        "target_screen_name": "ELIANADUITAMA",
        "source_id": 1351202858629263361
    },
    {
        "target_id": 925081063122194432,
        "target_screen_name": "Klaus_Lex",
        "source_id": 1351202858629263361
    },
    {
        "target_id": 94352635,
        "target_screen_name": "christianmunthe",
        "source_id": 1351202858629263361
    },
    {
        "target_id": 331903870,
        "target_screen_name": "SabKupu",
        "source_id": 1351202858629263361
    },
    {
        "target_id": 1918503584,
        "target_screen_name": "StellaRyuk",
        "source_id": 1351202858629263361
    },
    {
        "target_id": 1381260247428386816,
        "target_screen_name": "certAInify",
        "source_id": 1351202858629263361
    },
    {
        "target_id": 1318735753904611332,
        "target_screen_name": "AIEthicsWatch",
        "source_id": 1351202858629263361
    },
    {
        "target_id": 756480184329572352,
        "target_screen_name": "LeonieBeining",
        "source_id": 1351202858629263361
    },
    {
        "target_id": 2344616451,
        "target_screen_name": "AstonLiz",
        "source_id": 1351202858629263361
    },
    {
        "target_id": 48632913,
        "target_screen_name": "chaddechant",
        "source_id": 1351202858629263361
    },
    {
        "target_id": 1400407060311851009,
        "target_screen_name": "acai2021",
        "source_id": 1351202858629263361
    },
    {
        "target_id": 153359125,
        "target_screen_name": "AltheaFlus",
        "source_id": 1351202858629263361
    },
    {
        "target_id": 44375285,
        "target_screen_name": "devilfoods",
        "source_id": 1351202858629263361
    },
    {
        "target_id": 1048934975943442433,
        "target_screen_name": "CyberSobiecki",
        "source_id": 1351202858629263361
    },
    {
        "target_id": 3290368221,
        "target_screen_name": "Retrozeitgeist",
        "source_id": 1351202858629263361
    },
    {
        "target_id": 291619012,
        "target_screen_name": "Damini_Satija",
        "source_id": 1351202858629263361
    },
    {
        "target_id": 1400514769178800133,
        "target_screen_name": "archivalcons",
        "source_id": 1351202858629263361
    },
    {
        "target_id": 597528861,
        "target_screen_name": "doctorSdS",
        "source_id": 1351202858629263361
    },
    {
        "target_id": 707476741552541699,
        "target_screen_name": "zoe_christoff",
        "source_id": 1351202858629263361
    },
    {
        "target_id": 1070687922742018049,
        "target_screen_name": "AISustCenter",
        "source_id": 1351202858629263361
    },
    {
        "target_id": 1274648431919857666,
        "target_screen_name": "neagustan",
        "source_id": 1351202858629263361
    },
    {
        "target_id": 1389217297215131650,
        "target_screen_name": "ECLT_Venice",
        "source_id": 1351202858629263361
    },
    {
        "target_id": 4816522980,
        "target_screen_name": "CamusA1",
        "source_id": 1351202858629263361
    },
    {
        "target_id": 1109888426516451328,
        "target_screen_name": "Kdanziger2",
        "source_id": 1351202858629263361
    },
    {
        "target_id": 1302509687439491073,
        "target_screen_name": "GulsenGulerdl",
        "source_id": 1351202858629263361
    },
    {
        "target_id": 435270280,
        "target_screen_name": "Citizen_Drain",
        "source_id": 1351202858629263361
    },
    {
        "target_id": 804174301914169344,
        "target_screen_name": "drpamelalirio",
        "source_id": 1351202858629263361
    },
    {
        "target_id": 1498293151,
        "target_screen_name": "DigitalSocietyL",
        "source_id": 1351202858629263361
    },
    {
        "target_id": 2360317543,
        "target_screen_name": "JuanRodriPrensa",
        "source_id": 1351202858629263361
    },
    {
        "target_id": 15159154,
        "target_screen_name": "Humlab",
        "source_id": 1351202858629263361
    },
    {
        "target_id": 1410956727177068545,
        "target_screen_name": "CleberIkeda",
        "source_id": 1351202858629263361
    },
    {
        "target_id": 1019159386621652992,
        "target_screen_name": "kira_lao",
        "source_id": 1351202858629263361
    },
    {
        "target_id": 1231762111258251264,
        "target_screen_name": "_wandamunoz",
        "source_id": 1351202858629263361
    },
    {
        "target_id": 16366472,
        "target_screen_name": "simonlindgren",
        "source_id": 1351202858629263361
    },
    {
        "target_id": 1422338924295475208,
        "target_screen_name": "SpursCentered",
        "source_id": 1351202858629263361
    },
    {
        "target_id": 81259714,
        "target_screen_name": "angelescortesi",
        "source_id": 1351202858629263361
    },
    {
        "target_id": 778904697293996032,
        "target_screen_name": "WorldSummitAI",
        "source_id": 1351202858629263361
    },
    {
        "target_id": 207056399,
        "target_screen_name": "HPierrette",
        "source_id": 1351202858629263361
    },
    {
        "target_id": 25493114,
        "target_screen_name": "JuanDGut",
        "source_id": 1351202858629263361
    },
    {
        "target_id": 473969150,
        "target_screen_name": "palakdudani",
        "source_id": 1351202858629263361
    },
    {
        "target_id": 1288464628184494080,
        "target_screen_name": "samlaren2",
        "source_id": 1351202858629263361
    },
    {
        "target_id": 1346451618,
        "target_screen_name": "evopma",
        "source_id": 1351202858629263361
    },
    {
        "target_id": 1417184072150011908,
        "target_screen_name": "aamas2022",
        "source_id": 1351202858629263361
    },
    {
        "target_id": 1420910760105025541,
        "target_screen_name": "_suzi_austin",
        "source_id": 1351202858629263361
    },
    {
        "target_id": 4295263768,
        "target_screen_name": "raja_chatila",
        "source_id": 1351202858629263361
    },
    {
        "target_id": 15267017,
        "target_screen_name": "marigo",
        "source_id": 1351202858629263361
    },
    {
        "target_id": 1064169500977913858,
        "target_screen_name": "MaximilianKien2",
        "source_id": 1351202858629263361
    },
    {
        "target_id": 809682428,
        "target_screen_name": "allamarinara",
        "source_id": 1351202858629263361
    },
    {
        "target_id": 68541706,
        "target_screen_name": "asilvaguilherme",
        "source_id": 1351202858629263361
    },
    {
        "target_id": 1253888912872931330,
        "target_screen_name": "Catymunozg",
        "source_id": 1351202858629263361
    },
    {
        "target_id": 2313653275,
        "target_screen_name": "NFUnions",
        "source_id": 1351202858629263361
    },
    {
        "target_id": 57690743,
        "target_screen_name": "julianamichelon",
        "source_id": 1351202858629263361
    },
    {
        "target_id": 1349757195278315522,
        "target_screen_name": "wairobotics",
        "source_id": 1351202858629263361
    },
    {
        "target_id": 89649126,
        "target_screen_name": "xziouvelou",
        "source_id": 1351202858629263361
    },
    {
        "target_id": 1281882757,
        "target_screen_name": "mnaveedsattar",
        "source_id": 1351202858629263361
    },
    {
        "target_id": 558290704,
        "target_screen_name": "AdamWickberg_",
        "source_id": 1351202858629263361
    },
    {
        "target_id": 420974392,
        "target_screen_name": "EmadYaghmaei",
        "source_id": 1351202858629263361
    },
    {
        "target_id": 849060834466832384,
        "target_screen_name": "APPG_AI",
        "source_id": 1351202858629263361
    },
    {
        "target_id": 888824689958715392,
        "target_screen_name": "anisa_anisa_",
        "source_id": 1351202858629263361
    },
    {
        "target_id": 1006091107816628225,
        "target_screen_name": "ResponsibleAI",
        "source_id": 1351202858629263361
    },
    {
        "target_id": 4407223274,
        "target_screen_name": "phebe_vayanos",
        "source_id": 1351202858629263361
    },
    {
        "target_id": 1075491530960293888,
        "target_screen_name": "xrisk_",
        "source_id": 1351202858629263361
    },
    {
        "target_id": 33672095,
        "target_screen_name": "FredrikHeintz",
        "source_id": 1351202858629263361
    },
    {
        "target_id": 1318962279346589698,
        "target_screen_name": "SoloCarla1",
        "source_id": 1351202858629263361
    },
    {
        "target_id": 801850213,
        "target_screen_name": "SethBergeson",
        "source_id": 1351202858629263361
    },
    {
        "target_id": 1400752401729167362,
        "target_screen_name": "TrigoKramcsak",
        "source_id": 1351202858629263361
    },
    {
        "target_id": 386538440,
        "target_screen_name": "DalithSteiger",
        "source_id": 1351202858629263361
    },
    {
        "target_id": 1138822334423412736,
        "target_screen_name": "mustafa__cavus",
        "source_id": 1351202858629263361
    },
    {
        "target_id": 218502051,
        "target_screen_name": "margiemeacham",
        "source_id": 1351202858629263361
    },
    {
        "target_id": 49257537,
        "target_screen_name": "EFFE_CI_UD",
        "source_id": 1351202858629263361
    },
    {
        "target_id": 834030478042738689,
        "target_screen_name": "nikhil07prakash",
        "source_id": 1351202858629263361
    },
    {
        "target_id": 1135623683106643969,
        "target_screen_name": "wasp_hs",
        "source_id": 1351202858629263361
    },
    {
        "target_id": 728729785,
        "target_screen_name": "dryellowbean",
        "source_id": 1351202858629263361
    },
    {
        "target_id": 2996579132,
        "target_screen_name": "ElmiraYad",
        "source_id": 1351202858629263361
    },
    {
        "target_id": 739404319,
        "target_screen_name": "carlanguerraz",
        "source_id": 1351202858629263361
    },
    {
        "target_id": 798186963895365633,
        "target_screen_name": "ChipsAndTweets",
        "source_id": 1351202858629263361
    },
    {
        "target_id": 1078342838612623360,
        "target_screen_name": "CesarTacla",
        "source_id": 1351202858629263361
    },
    {
        "target_id": 1205801853340000256,
        "target_screen_name": "Ai4Eo",
        "source_id": 1351202858629263361
    },
    {
        "target_id": 1326689941582192641,
        "target_screen_name": "DrRicardoAguil3",
        "source_id": 1351202858629263361
    },
    {
        "target_id": 1318128567767662595,
        "target_screen_name": "LIV_consulting",
        "source_id": 1351202858629263361
    },
    {
        "target_id": 1202518033891287040,
        "target_screen_name": "SiinaRaskulla",
        "source_id": 1351202858629263361
    },
    {
        "target_id": 982234588075376647,
        "target_screen_name": "JResInnov",
        "source_id": 1351202858629263361
    },
    {
        "target_id": 1296498237227008001,
        "target_screen_name": "IMiminllari",
        "source_id": 1351202858629263361
    },
    {
        "target_id": 1354141547164545034,
        "target_screen_name": "onlineopportun",
        "source_id": 1351202858629263361
    },
    {
        "target_id": 1382969845835304960,
        "target_screen_name": "lumosmassimo",
        "source_id": 1351202858629263361
    },
    {
        "target_id": 2999992556,
        "target_screen_name": "wimlds",
        "source_id": 1351202858629263361
    },
    {
        "target_id": 19269506,
        "target_screen_name": "mvaldenegro",
        "source_id": 1351202858629263361
    },
    {
        "target_id": 247658865,
        "target_screen_name": "mbirna",
        "source_id": 1351202858629263361
    },
    {
        "target_id": 186936963,
        "target_screen_name": "ppverbeek",
        "source_id": 1351202858629263361
    },
    {
        "target_id": 18212578,
        "target_screen_name": "marcsteen",
        "source_id": 1351202858629263361
    },
    {
        "target_id": 140112186,
        "target_screen_name": "RobWortham",
        "source_id": 1351202858629263361
    },
    {
        "target_id": 2852028033,
        "target_screen_name": "DianaMocanuM",
        "source_id": 1351202858629263361
    },
    {
        "target_id": 1103585141245530113,
        "target_screen_name": "RUEBES_adir",
        "source_id": 1351202858629263361
    },
    {
        "target_id": 262164735,
        "target_screen_name": "rc_serban",
        "source_id": 1351202858629263361
    },
    {
        "target_id": 4863110375,
        "target_screen_name": "Kate_Boddington",
        "source_id": 1351202858629263361
    },
    {
        "target_id": 6857072,
        "target_screen_name": "amarashar",
        "source_id": 1351202858629263361
    },
    {
        "target_id": 1087272633412927489,
        "target_screen_name": "Prady029",
        "source_id": 1351202858629263361
    },
    {
        "target_id": 1619666256,
        "target_screen_name": "informusiccs",
        "source_id": 1351202858629263361
    },
    {
        "target_id": 1263749739142619136,
        "target_screen_name": "decastro_bruna",
        "source_id": 1351202858629263361
    },
    {
        "target_id": 441700002,
        "target_screen_name": "caramiaux",
        "source_id": 1351202858629263361
    },
    {
        "target_id": 2465754992,
        "target_screen_name": "swathi_matwog",
        "source_id": 1351202858629263361
    },
    {
        "target_id": 2179853022,
        "target_screen_name": "MargaretaGroth",
        "source_id": 1351202858629263361
    },
    {
        "target_id": 14996765,
        "target_screen_name": "esteban_g_r_",
        "source_id": 1351202858629263361
    },
    {
        "target_id": 43864523,
        "target_screen_name": "kabulkurniawan",
        "source_id": 1351202858629263361
    },
    {
        "target_id": 73395185,
        "target_screen_name": "freakyseedwoman",
        "source_id": 1351202858629263361
    },
    {
        "target_id": 860113672026247168,
        "target_screen_name": "ayushcic",
        "source_id": 1351202858629263361
    },
    {
        "target_id": 1321916753614671872,
        "target_screen_name": "lloyd2k01",
        "source_id": 1351202858629263361
    },
    {
        "target_id": 1149694300738994179,
        "target_screen_name": "owbitar",
        "source_id": 1351202858629263361
    },
    {
        "target_id": 1479360943,
        "target_screen_name": "cerenoyy",
        "source_id": 1351202858629263361
    },
    {
        "target_id": 82210553,
        "target_screen_name": "2ghz",
        "source_id": 1351202858629263361
    },
    {
        "target_id": 1341742829257764864,
        "target_screen_name": "CognitiveFor",
        "source_id": 1351202858629263361
    },
    {
        "target_id": 1374800780801232906,
        "target_screen_name": "IsabelG64687224",
        "source_id": 1351202858629263361
    },
    {
        "target_id": 160362994,
        "target_screen_name": "magdalenaosimk",
        "source_id": 1351202858629263361
    },
    {
        "target_id": 798160916,
        "target_screen_name": "AlexMoltzau",
        "source_id": 1351202858629263361
    },
    {
        "target_id": 366640645,
        "target_screen_name": "MostafaSaket",
        "source_id": 1351202858629263361
    },
    {
        "target_id": 1004624913225969669,
        "target_screen_name": "linacomet",
        "source_id": 1351202858629263361
    },
    {
        "target_id": 468741382,
        "target_screen_name": "GregoriMattia07",
        "source_id": 1351202858629263361
    },
    {
        "target_id": 15242431,
        "target_screen_name": "atomax",
        "source_id": 1351202858629263361
    },
    {
        "target_id": 277600131,
        "target_screen_name": "AndreNemeh",
        "source_id": 1351202858629263361
    },
    {
        "target_id": 1219575972170813440,
        "target_screen_name": "ThomasZenkl",
        "source_id": 1351202858629263361
    },
    {
        "target_id": 20632934,
        "target_screen_name": "BadmotorF",
        "source_id": 1351202858629263361
    },
    {
        "target_id": 271498416,
        "target_screen_name": "PValoggia",
        "source_id": 1351202858629263361
    },
    {
        "target_id": 742063635003002881,
        "target_screen_name": "TiinaValonen",
        "source_id": 1351202858629263361
    },
    {
        "target_id": 2251083366,
        "target_screen_name": "MarcFaddoul",
        "source_id": 1351202858629263361
    },
    {
        "target_id": 1085830202603827200,
        "target_screen_name": "ChalmersAI",
        "source_id": 1351202858629263361
    },
    {
        "target_id": 1260578233336111106,
        "target_screen_name": "TessaDarbyshire",
        "source_id": 1351202858629263361
    },
    {
        "target_id": 953584610042171392,
        "target_screen_name": "LucasCardiell",
        "source_id": 1351202858629263361
    },
    {
        "target_id": 130401036,
        "target_screen_name": "FransafM",
        "source_id": 1351202858629263361
    },
    {
        "target_id": 315292935,
        "target_screen_name": "dzarevska",
        "source_id": 1351202858629263361
    },
    {
        "target_id": 116231527,
        "target_screen_name": "DanTooDee",
        "source_id": 1351202858629263361
    },
    {
        "target_id": 1965857742,
        "target_screen_name": "HMDevinney",
        "source_id": 1351202858629263361
    },
    {
        "target_id": 1215911177903058945,
        "target_screen_name": "HenniParviainen",
        "source_id": 1351202858629263361
    },
    {
        "target_id": 761318694,
        "target_screen_name": "kristina_t_t",
        "source_id": 1351202858629263361
    },
    {
        "target_id": 1261710344189358080,
        "target_screen_name": "Patrick_M_Econ",
        "source_id": 1351202858629263361
    },
    {
        "target_id": 219385074,
        "target_screen_name": "eren__sozuer",
        "source_id": 1351202858629263361
    },
    {
        "target_id": 3143020964,
        "target_screen_name": "MartimBrandao",
        "source_id": 1351202858629263361
    },
    {
        "target_id": 3302765692,
        "target_screen_name": "FranciscasHoy",
        "source_id": 1351202858629263361
    },
    {
        "target_id": 710811286263767040,
        "target_screen_name": "tachtler",
        "source_id": 1351202858629263361
    },
    {
        "target_id": 34746952,
        "target_screen_name": "pdxnicolle",
        "source_id": 1351202858629263361
    },
    {
        "target_id": 1052929408804245504,
        "target_screen_name": "AandVNetwork",
        "source_id": 1351202858629263361
    },
    {
        "target_id": 113951132,
        "target_screen_name": "iluaces",
        "source_id": 1351202858629263361
    },
    {
        "target_id": 192086031,
        "target_screen_name": "alramadona",
        "source_id": 1351202858629263361
    },
    {
        "target_id": 1013204362884206592,
        "target_screen_name": "bermudez_ademir",
        "source_id": 1351202858629263361
    },
    {
        "target_id": 1093067633379946497,
        "target_screen_name": "clodicaurelie",
        "source_id": 1351202858629263361
    },
    {
        "target_id": 188734426,
        "target_screen_name": "iamdejan",
        "source_id": 1351202858629263361
    },
    {
        "target_id": 1072463091626074112,
        "target_screen_name": "ClawiFig",
        "source_id": 1351202858629263361
    },
    {
        "target_id": 123511685,
        "target_screen_name": "xiaoweih",
        "source_id": 1351202858629263361
    },
    {
        "target_id": 1356967469504692224,
        "target_screen_name": "dih4ai",
        "source_id": 1351202858629263361
    },
    {
        "target_id": 1343839448170188800,
        "target_screen_name": "ETAPAS_EU",
        "source_id": 1351202858629263361
    },
    {
        "target_id": 98938785,
        "target_screen_name": "DavesBrewFarm",
        "source_id": 1351202858629263361
    },
    {
        "target_id": 2496725482,
        "target_screen_name": "fabiofossa36",
        "source_id": 1351202858629263361
    },
    {
        "target_id": 396385077,
        "target_screen_name": "dkrn3",
        "source_id": 1351202858629263361
    },
    {
        "target_id": 931967049789792257,
        "target_screen_name": "AI_ilachinski",
        "source_id": 1351202858629263361
    },
    {
        "target_id": 95488935,
        "target_screen_name": "vgalaz",
        "source_id": 1351202858629263361
    },
    {
        "target_id": 1100603022,
        "target_screen_name": "nilsenwald",
        "source_id": 1351202858629263361
    },
    {
        "target_id": 1685825136,
        "target_screen_name": "GrandpaRobot",
        "source_id": 1351202858629263361
    },
    {
        "target_id": 1124265687755755520,
        "target_screen_name": "WASP_Research",
        "source_id": 1351202858629263361
    },
    {
        "target_id": 819155095,
        "target_screen_name": "martafernjim",
        "source_id": 1351202858629263361
    },
    {
        "target_id": 1362984396,
        "target_screen_name": "DinoPedreschi",
        "source_id": 1351202858629263361
    },
    {
        "target_id": 1010775700872355841,
        "target_screen_name": "RistoUuk",
        "source_id": 1351202858629263361
    },
    {
        "target_id": 1005055894734897153,
        "target_screen_name": "SciTechDiploHub",
        "source_id": 1351202858629263361
    },
    {
        "target_id": 1298259253224849412,
        "target_screen_name": "ParzivalPtnrs",
        "source_id": 1351202858629263361
    },
    {
        "target_id": 285599650,
        "target_screen_name": "KennethBodin",
        "source_id": 1351202858629263361
    },
    {
        "target_id": 740116393262256128,
        "target_screen_name": "lottielane_",
        "source_id": 1351202858629263361
    },
    {
        "target_id": 53079366,
        "target_screen_name": "lausartori",
        "source_id": 1351202858629263361
    },
    {
        "target_id": 1082223279761473537,
        "target_screen_name": "AHuckelba",
        "source_id": 1351202858629263361
    },
    {
        "target_id": 8168662,
        "target_screen_name": "adamleonsmith",
        "source_id": 1351202858629263361
    },
    {
        "target_id": 332194654,
        "target_screen_name": "DavidTournadre",
        "source_id": 1351202858629263361
    },
    {
        "target_id": 1026960115256188929,
        "target_screen_name": "andreea_g2011M",
        "source_id": 1351202858629263361
    },
    {
        "target_id": 1241783603534745604,
        "target_screen_name": "TeresaScantamb1",
        "source_id": 1351202858629263361
    },
    {
        "target_id": 1252691183878508544,
        "target_screen_name": "FrancescaFoffa1",
        "source_id": 1351202858629263361
    },
    {
        "target_id": 58018339,
        "target_screen_name": "DebbieWoodward",
        "source_id": 1351202858629263361
    },
    {
        "target_id": 1317142153462796289,
        "target_screen_name": "OEIAC_UdG",
        "source_id": 1351202858629263361
    },
    {
        "target_id": 446461168,
        "target_screen_name": "mireillemoret",
        "source_id": 1351202858629263361
    },
    {
        "target_id": 108712683,
        "target_screen_name": "ish_trendsetter",
        "source_id": 1351202858629263361
    },
    {
        "target_id": 3635837595,
        "target_screen_name": "AllaKos_Dev",
        "source_id": 1351202858629263361
    },
    {
        "target_id": 2523343148,
        "target_screen_name": "ralucaETIQ",
        "source_id": 1351202858629263361
    },
    {
        "target_id": 1228250640,
        "target_screen_name": "OseroShadrackT",
        "source_id": 1351202858629263361
    },
    {
        "target_id": 1210152975232126976,
        "target_screen_name": "ChidinmaUdechu2",
        "source_id": 1351202858629263361
    },
    {
        "target_id": 1339491930,
        "target_screen_name": "el_lehagre",
        "source_id": 1351202858629263361
    },
    {
        "target_id": 1010898326,
        "target_screen_name": "Dowellenough",
        "source_id": 1351202858629263361
    },
    {
        "target_id": 1178671860134940672,
        "target_screen_name": "BoganiRonny",
        "source_id": 1351202858629263361
    },
    {
        "target_id": 1370317081,
        "target_screen_name": "SylvieSaget",
        "source_id": 1351202858629263361
    },
    {
        "target_id": 454897936,
        "target_screen_name": "TanDuarte",
        "source_id": 1351202858629263361
    },
    {
        "target_id": 16556796,
        "target_screen_name": "maria_axente",
        "source_id": 1351202858629263361
    },
    {
        "target_id": 576919217,
        "target_screen_name": "sesdun",
        "source_id": 1351202858629263361
    },
    {
        "target_id": 60723919,
        "target_screen_name": "gutatcuco",
        "source_id": 1351202858629263361
    },
    {
        "target_id": 2376855960,
        "target_screen_name": "lois_vanhee",
        "source_id": 1351202858629263361
    },
    {
        "target_id": 11620,
        "target_screen_name": "kortuem",
        "source_id": 1351202858629263361
    },
    {
        "target_id": 1090021224175026176,
        "target_screen_name": "iterrucha",
        "source_id": 1351202858629263361
    },
    {
        "target_id": 3302896814,
        "target_screen_name": "greischauer",
        "source_id": 1351202858629263361
    },
    {
        "target_id": 910485197405196289,
        "target_screen_name": "Lauren_wbg",
        "source_id": 1351202858629263361
    },
    {
        "target_id": 3045104705,
        "target_screen_name": "bereniceboutin",
        "source_id": 1351202858629263361
    },
    {
        "target_id": 2556357312,
        "target_screen_name": "didem_korkmaz",
        "source_id": 1351202858629263361
    },
    {
        "target_id": 2357079560,
        "target_screen_name": "RecklessCoding",
        "source_id": 1351202858629263361
    },
    {
        "target_id": 1048216219,
        "target_screen_name": "eleni_ioakeim",
        "source_id": 1351202858629263361
    },
    {
        "target_id": 102404869,
        "target_screen_name": "unimatrix9",
        "source_id": 1351202858629263361
    },
    {
        "target_id": 906555858313674752,
        "target_screen_name": "ParetoJulia",
        "source_id": 1351202858629263361
    },
    {
        "target_id": 339941459,
        "target_screen_name": "RobMcCargow",
        "source_id": 1351202858629263361
    },
    {
        "target_id": 387611652,
        "target_screen_name": "GCSCS_RuG",
        "source_id": 1351202858629263361
    },
    {
        "target_id": 1265596697633271808,
        "target_screen_name": "Ch_Hogberg",
        "source_id": 1351202858629263361
    },
    {
        "target_id": 888002138139504640,
        "target_screen_name": "YellowBicyclist",
        "source_id": 1351202858629263361
    },
    {
        "target_id": 1000023384531636224,
        "target_screen_name": "AnoukvanMaris",
        "source_id": 1351202858629263361
    },
    {
        "target_id": 177993199,
        "target_screen_name": "fborgesius",
        "source_id": 1351202858629263361
    },
    {
        "target_id": 756040164149977089,
        "target_screen_name": "tala201677",
        "source_id": 1351202858629263361
    },
    {
        "target_id": 1082232363302731776,
        "target_screen_name": "AI4EU",
        "source_id": 1351202858629263361
    },
    {
        "target_id": 208660605,
        "target_screen_name": "remellema",
        "source_id": 1351202858629263361
    },
    {
        "target_id": 244060651,
        "target_screen_name": "nielsvberkel",
        "source_id": 1351202858629263361
    },
    {
        "target_id": 2870393725,
        "target_screen_name": "Irena_nest",
        "source_id": 1351202858629263361
    },
    {
        "target_id": 119842111,
        "target_screen_name": "LaoisNi",
        "source_id": 1351202858629263361
    },
    {
        "target_id": 450938173,
        "target_screen_name": "pcontrerasnet",
        "source_id": 1351202858629263361
    },
    {
        "target_id": 127414067,
        "target_screen_name": "roeldobbe",
        "source_id": 1351202858629263361
    },
    {
        "target_id": 24504364,
        "target_screen_name": "spillteori",
        "source_id": 1351202858629263361
    },
    {
        "target_id": 271601706,
        "target_screen_name": "vdignum",
        "source_id": 1351202858629263361
    },
    {
        "target_id": 191942208,
        "target_screen_name": "jc_nieves",
        "source_id": 1351202858629263361
    },
    {
        "target_id": 76312278,
        "target_screen_name": "mendezjulian",
        "source_id": 1351202858629263361
    },
    {
        "target_id": 620962350,
        "target_screen_name": "bandadmoebius",
        "source_id": 1351202858629263361
    },
    {
        "target_id": 197407793,
        "target_screen_name": "Zahoorgtech",
        "source_id": 1351202858629263361
    }
]