[
    {
        "target_id": 1192625531025608705,
        "target_screen_name": "VCBrags",
        "source_id": 223439979
    },
    {
        "target_id": 1683691309,
        "target_screen_name": "paulorrsj",
        "source_id": 223439979
    },
    {
        "target_id": 558876883,
        "target_screen_name": "Fede_mister",
        "source_id": 223439979
    },
    {
        "target_id": 970418258674376706,
        "target_screen_name": "dilettahuyskes_",
        "source_id": 223439979
    },
    {
        "target_id": 201432428,
        "target_screen_name": "AI_x_IA",
        "source_id": 223439979
    },
    {
        "target_id": 904706175765270529,
        "target_screen_name": "BigData4Inno",
        "source_id": 223439979
    },
    {
        "target_id": 34042766,
        "target_screen_name": "McKinsey",
        "source_id": 223439979
    },
    {
        "target_id": 1183747500848701441,
        "target_screen_name": "luciano_mocci",
        "source_id": 223439979
    },
    {
        "target_id": 20698669,
        "target_screen_name": "regularjoy",
        "source_id": 223439979
    },
    {
        "target_id": 152933590,
        "target_screen_name": "AMRITAedu",
        "source_id": 223439979
    },
    {
        "target_id": 1097451709,
        "target_screen_name": "AmritaVLabs",
        "source_id": 223439979
    },
    {
        "target_id": 706804891,
        "target_screen_name": "amritabiotech",
        "source_id": 223439979
    },
    {
        "target_id": 978995726041665536,
        "target_screen_name": "DataBench_eu",
        "source_id": 223439979
    },
    {
        "target_id": 1230406184450056195,
        "target_screen_name": "JovanSt15366446",
        "source_id": 223439979
    },
    {
        "target_id": 2930156653,
        "target_screen_name": "WorldTrendsInfo",
        "source_id": 223439979
    },
    {
        "target_id": 951895590,
        "target_screen_name": "Tecno_Corriere",
        "source_id": 223439979
    },
    {
        "target_id": 578881641,
        "target_screen_name": "DeloitteDigital",
        "source_id": 223439979
    },
    {
        "target_id": 17163609,
        "target_screen_name": "mrogati",
        "source_id": 223439979
    },
    {
        "target_id": 216939636,
        "target_screen_name": "AndrewYNg",
        "source_id": 223439979
    },
    {
        "target_id": 390642467,
        "target_screen_name": "Triwu",
        "source_id": 223439979
    },
    {
        "target_id": 42954145,
        "target_screen_name": "aperdichizzi",
        "source_id": 223439979
    },
    {
        "target_id": 62079398,
        "target_screen_name": "bcominelli",
        "source_id": 223439979
    },
    {
        "target_id": 409839478,
        "target_screen_name": "infocamere",
        "source_id": 223439979
    },
    {
        "target_id": 14332671,
        "target_screen_name": "DFKI",
        "source_id": 223439979
    },
    {
        "target_id": 1092735302,
        "target_screen_name": "MISE_GOV",
        "source_id": 223439979
    },
    {
        "target_id": 837341223694249984,
        "target_screen_name": "nordicinst",
        "source_id": 223439979
    },
    {
        "target_id": 1172174046697578496,
        "target_screen_name": "Waterjade3",
        "source_id": 223439979
    },
    {
        "target_id": 38135277,
        "target_screen_name": "mcanducci",
        "source_id": 223439979
    },
    {
        "target_id": 2312648996,
        "target_screen_name": "CristianoRadael",
        "source_id": 223439979
    },
    {
        "target_id": 1082232363302731776,
        "target_screen_name": "AI4EU",
        "source_id": 223439979
    },
    {
        "target_id": 253099487,
        "target_screen_name": "polimi",
        "source_id": 223439979
    },
    {
        "target_id": 2834887269,
        "target_screen_name": "Osserv_Digital",
        "source_id": 223439979
    },
    {
        "target_id": 1322691,
        "target_screen_name": "neilpatel",
        "source_id": 223439979
    },
    {
        "target_id": 806499446284570624,
        "target_screen_name": "analytics_n",
        "source_id": 223439979
    },
    {
        "target_id": 931175825998835713,
        "target_screen_name": "PID_CamCom",
        "source_id": 223439979
    },
    {
        "target_id": 462775249,
        "target_screen_name": "StartUpEU",
        "source_id": 223439979
    },
    {
        "target_id": 108286674,
        "target_screen_name": "BernardMarr",
        "source_id": 223439979
    },
    {
        "target_id": 1641208627,
        "target_screen_name": "sartori__andrea",
        "source_id": 223439979
    },
    {
        "target_id": 2909543129,
        "target_screen_name": "TRIResearch_",
        "source_id": 223439979
    },
    {
        "target_id": 119711344,
        "target_screen_name": "wireditalia",
        "source_id": 223439979
    },
    {
        "target_id": 4008749200,
        "target_screen_name": "Agenda_Digitale",
        "source_id": 223439979
    },
    {
        "target_id": 17333183,
        "target_screen_name": "sarahaustin",
        "source_id": 223439979
    },
    {
        "target_id": 1323115201,
        "target_screen_name": "BigDataMinded",
        "source_id": 223439979
    },
    {
        "target_id": 22160201,
        "target_screen_name": "fpmarconi",
        "source_id": 223439979
    },
    {
        "target_id": 950447567992688641,
        "target_screen_name": "LindaGrass0",
        "source_id": 223439979
    },
    {
        "target_id": 373883201,
        "target_screen_name": "VladoBotsvadze",
        "source_id": 223439979
    },
    {
        "target_id": 1207169726280941568,
        "target_screen_name": "data_lessons",
        "source_id": 223439979
    },
    {
        "target_id": 534563976,
        "target_screen_name": "KirkDBorne",
        "source_id": 223439979
    },
    {
        "target_id": 842303924170289152,
        "target_screen_name": "fodark",
        "source_id": 223439979
    },
    {
        "target_id": 2833681222,
        "target_screen_name": "SpinLabLeipzig",
        "source_id": 223439979
    },
    {
        "target_id": 395972891,
        "target_screen_name": "GiorgiaLodi",
        "source_id": 223439979
    },
    {
        "target_id": 984109342315163648,
        "target_screen_name": "agriotlab",
        "source_id": 223439979
    },
    {
        "target_id": 934029315922186240,
        "target_screen_name": "stardusth2020",
        "source_id": 223439979
    },
    {
        "target_id": 170711160,
        "target_screen_name": "5anatre",
        "source_id": 223439979
    },
    {
        "target_id": 923639883767406592,
        "target_screen_name": "TNSalute",
        "source_id": 223439979
    },
    {
        "target_id": 915514148787822592,
        "target_screen_name": "speckandtech",
        "source_id": 223439979
    },
    {
        "target_id": 2180823319,
        "target_screen_name": "AmditisA",
        "source_id": 223439979
    },
    {
        "target_id": 1326373002,
        "target_screen_name": "gigicapello",
        "source_id": 223439979
    },
    {
        "target_id": 839217265,
        "target_screen_name": "ariannaconci",
        "source_id": 223439979
    },
    {
        "target_id": 1178970996340080640,
        "target_screen_name": "tessa_agritech",
        "source_id": 223439979
    },
    {
        "target_id": 930058821694877696,
        "target_screen_name": "damdo",
        "source_id": 223439979
    },
    {
        "target_id": 5159271,
        "target_screen_name": "napo",
        "source_id": 223439979
    },
    {
        "target_id": 3362335599,
        "target_screen_name": "Pmeccatronica",
        "source_id": 223439979
    },
    {
        "target_id": 1346854957,
        "target_screen_name": "LVentureGroup",
        "source_id": 223439979
    },
    {
        "target_id": 1221225679,
        "target_screen_name": "BarbaraSani_",
        "source_id": 223439979
    },
    {
        "target_id": 838738092295061504,
        "target_screen_name": "eSIDES_eu",
        "source_id": 223439979
    },
    {
        "target_id": 1374717066,
        "target_screen_name": "UniTrento",
        "source_id": 223439979
    },
    {
        "target_id": 538108479,
        "target_screen_name": "Comonext_",
        "source_id": 223439979
    },
    {
        "target_id": 392179038,
        "target_screen_name": "LuciaChierchia",
        "source_id": 223439979
    },
    {
        "target_id": 223495740,
        "target_screen_name": "LUISSEnLabs",
        "source_id": 223439979
    },
    {
        "target_id": 819855864974675968,
        "target_screen_name": "Business_Chief",
        "source_id": 223439979
    },
    {
        "target_id": 2992525033,
        "target_screen_name": "Chatbots_Life",
        "source_id": 223439979
    },
    {
        "target_id": 782176007063298048,
        "target_screen_name": "ITAtradeagency",
        "source_id": 223439979
    },
    {
        "target_id": 485844145,
        "target_screen_name": "alinomilan",
        "source_id": 223439979
    },
    {
        "target_id": 2436625314,
        "target_screen_name": "_InesLaura",
        "source_id": 223439979
    },
    {
        "target_id": 250247611,
        "target_screen_name": "IAcornflake",
        "source_id": 223439979
    },
    {
        "target_id": 4243688073,
        "target_screen_name": "oascities",
        "source_id": 223439979
    },
    {
        "target_id": 856402700,
        "target_screen_name": "DunavNET",
        "source_id": 223439979
    },
    {
        "target_id": 2226555421,
        "target_screen_name": "GemmaGuilera10",
        "source_id": 223439979
    },
    {
        "target_id": 1427397266,
        "target_screen_name": "NetTechEU",
        "source_id": 223439979
    },
    {
        "target_id": 839138334131773440,
        "target_screen_name": "ClabTrento",
        "source_id": 223439979
    },
    {
        "target_id": 725618777891704833,
        "target_screen_name": "UtaWehn",
        "source_id": 223439979
    },
    {
        "target_id": 51861120,
        "target_screen_name": "mig_garcia",
        "source_id": 223439979
    },
    {
        "target_id": 220624570,
        "target_screen_name": "romifog",
        "source_id": 223439979
    },
    {
        "target_id": 3298859685,
        "target_screen_name": "zabala_eu",
        "source_id": 223439979
    },
    {
        "target_id": 521466657,
        "target_screen_name": "Zabala_IC",
        "source_id": 223439979
    },
    {
        "target_id": 833981208421883904,
        "target_screen_name": "edincubator",
        "source_id": 223439979
    },
    {
        "target_id": 2242881544,
        "target_screen_name": "traverso_paolo",
        "source_id": 223439979
    },
    {
        "target_id": 45377713,
        "target_screen_name": "MilenaBigatto",
        "source_id": 223439979
    },
    {
        "target_id": 9499372,
        "target_screen_name": "mseniga",
        "source_id": 223439979
    },
    {
        "target_id": 960855740,
        "target_screen_name": "ericaparis",
        "source_id": 223439979
    },
    {
        "target_id": 29207596,
        "target_screen_name": "zidia",
        "source_id": 223439979
    },
    {
        "target_id": 157981564,
        "target_screen_name": "EU_Commission",
        "source_id": 223439979
    },
    {
        "target_id": 591776330,
        "target_screen_name": "EUSciComm",
        "source_id": 223439979
    },
    {
        "target_id": 806850055,
        "target_screen_name": "enisa_eu",
        "source_id": 223439979
    },
    {
        "target_id": 205315827,
        "target_screen_name": "DigitalEU",
        "source_id": 223439979
    },
    {
        "target_id": 2842558252,
        "target_screen_name": "BDVA_PPP",
        "source_id": 223439979
    },
    {
        "target_id": 378512858,
        "target_screen_name": "Vittoriobanfi",
        "source_id": 223439979
    },
    {
        "target_id": 2921455108,
        "target_screen_name": "olgus",
        "source_id": 223439979
    },
    {
        "target_id": 3075208463,
        "target_screen_name": "FlinkForward",
        "source_id": 223439979
    },
    {
        "target_id": 1105568625853976582,
        "target_screen_name": "IoTNextClub1",
        "source_id": 223439979
    },
    {
        "target_id": 3044827841,
        "target_screen_name": "south_summit",
        "source_id": 223439979
    },
    {
        "target_id": 199680804,
        "target_screen_name": "thornysword",
        "source_id": 223439979
    },
    {
        "target_id": 16080324,
        "target_screen_name": "mhaklay",
        "source_id": 223439979
    },
    {
        "target_id": 874553428386746368,
        "target_screen_name": "JohanTordsson",
        "source_id": 223439979
    },
    {
        "target_id": 332444780,
        "target_screen_name": "alexborusan",
        "source_id": 223439979
    },
    {
        "target_id": 493926414,
        "target_screen_name": "elastisys",
        "source_id": 223439979
    },
    {
        "target_id": 858214680954900480,
        "target_screen_name": "LillyWu2017",
        "source_id": 223439979
    },
    {
        "target_id": 2192505872,
        "target_screen_name": "ctdski",
        "source_id": 223439979
    },
    {
        "target_id": 579754977,
        "target_screen_name": "Digital_Magics",
        "source_id": 223439979
    },
    {
        "target_id": 1536506010,
        "target_screen_name": "EconomyUp",
        "source_id": 223439979
    },
    {
        "target_id": 361084126,
        "target_screen_name": "TalentGardenit",
        "source_id": 223439979
    },
    {
        "target_id": 443933998,
        "target_screen_name": "chefuturo",
        "source_id": 223439979
    },
    {
        "target_id": 550809307,
        "target_screen_name": "INNOVUPnet",
        "source_id": 223439979
    },
    {
        "target_id": 1882264746,
        "target_screen_name": "CoderDojoTrento",
        "source_id": 223439979
    },
    {
        "target_id": 343401423,
        "target_screen_name": "NotteRicercaTN",
        "source_id": 223439979
    },
    {
        "target_id": 1598324696,
        "target_screen_name": "DH_FBK",
        "source_id": 223439979
    },
    {
        "target_id": 2602006797,
        "target_screen_name": "cippus",
        "source_id": 223439979
    },
    {
        "target_id": 1731414878,
        "target_screen_name": "KarinaMabellG",
        "source_id": 223439979
    },
    {
        "target_id": 1096318855453048832,
        "target_screen_name": "knowdive",
        "source_id": 223439979
    },
    {
        "target_id": 54514584,
        "target_screen_name": "skrco",
        "source_id": 223439979
    },
    {
        "target_id": 134818140,
        "target_screen_name": "mirkopresser",
        "source_id": 223439979
    },
    {
        "target_id": 4790351,
        "target_screen_name": "brynskov",
        "source_id": 223439979
    },
    {
        "target_id": 2901221562,
        "target_screen_name": "consorzio_tn",
        "source_id": 223439979
    },
    {
        "target_id": 824008095080792064,
        "target_screen_name": "ValantisTsiakos",
        "source_id": 223439979
    },
    {
        "target_id": 16297873,
        "target_screen_name": "fgranelli",
        "source_id": 223439979
    },
    {
        "target_id": 174589147,
        "target_screen_name": "ProvinciaTrento",
        "source_id": 223439979
    },
    {
        "target_id": 543774554,
        "target_screen_name": "HuffPostItalia",
        "source_id": 223439979
    },
    {
        "target_id": 160504297,
        "target_screen_name": "Accentureitalia",
        "source_id": 223439979
    },
    {
        "target_id": 26805663,
        "target_screen_name": "nicola_doppio",
        "source_id": 223439979
    },
    {
        "target_id": 420333757,
        "target_screen_name": "ngrigoletti",
        "source_id": 223439979
    },
    {
        "target_id": 420351046,
        "target_screen_name": "sole24ore",
        "source_id": 223439979
    },
    {
        "target_id": 3288318563,
        "target_screen_name": "about_big_data",
        "source_id": 223439979
    },
    {
        "target_id": 960831240,
        "target_screen_name": "RocksB91",
        "source_id": 223439979
    },
    {
        "target_id": 1039149863840169984,
        "target_screen_name": "IoTWeekAarhus",
        "source_id": 223439979
    },
    {
        "target_id": 760030872733151232,
        "target_screen_name": "MTStella",
        "source_id": 223439979
    },
    {
        "target_id": 96236831,
        "target_screen_name": "dimensionsrl",
        "source_id": 223439979
    },
    {
        "target_id": 1083414032093270016,
        "target_screen_name": "dmsaccelerator",
        "source_id": 223439979
    },
    {
        "target_id": 57775091,
        "target_screen_name": "alonsosilva",
        "source_id": 223439979
    },
    {
        "target_id": 975817275302330368,
        "target_screen_name": "IBMCommunity",
        "source_id": 223439979
    },
    {
        "target_id": 920921501121024001,
        "target_screen_name": "GELLIFYgroup",
        "source_id": 223439979
    },
    {
        "target_id": 492932268,
        "target_screen_name": "Idiap_ch",
        "source_id": 223439979
    },
    {
        "target_id": 808509187,
        "target_screen_name": "microsoftitalia",
        "source_id": 223439979
    },
    {
        "target_id": 2584370966,
        "target_screen_name": "DeGaRoss",
        "source_id": 223439979
    },
    {
        "target_id": 122458732,
        "target_screen_name": "fet_eu",
        "source_id": 223439979
    },
    {
        "target_id": 23116138,
        "target_screen_name": "ursulapala",
        "source_id": 223439979
    },
    {
        "target_id": 341057014,
        "target_screen_name": "maxnlit",
        "source_id": 223439979
    },
    {
        "target_id": 770287154639544320,
        "target_screen_name": "ITdigitalteam",
        "source_id": 223439979
    },
    {
        "target_id": 770285595780415488,
        "target_screen_name": "teamdigitaleIT",
        "source_id": 223439979
    },
    {
        "target_id": 2383600026,
        "target_screen_name": "AgidGov",
        "source_id": 223439979
    },
    {
        "target_id": 2387746514,
        "target_screen_name": "LauraSchelenz",
        "source_id": 223439979
    },
    {
        "target_id": 36337683,
        "target_screen_name": "davidepiazza",
        "source_id": 223439979
    },
    {
        "target_id": 133384903,
        "target_screen_name": "cgilsanz",
        "source_id": 223439979
    },
    {
        "target_id": 728604452,
        "target_screen_name": "ComuneMI",
        "source_id": 223439979
    },
    {
        "target_id": 3092716715,
        "target_screen_name": "ChiaBresciani",
        "source_id": 223439979
    },
    {
        "target_id": 539188025,
        "target_screen_name": "robi_cocco",
        "source_id": 223439979
    },
    {
        "target_id": 551775889,
        "target_screen_name": "niemihugaerts",
        "source_id": 223439979
    },
    {
        "target_id": 1303024741,
        "target_screen_name": "JuhaNummila",
        "source_id": 223439979
    },
    {
        "target_id": 87397938,
        "target_screen_name": "ForumVirium",
        "source_id": 223439979
    },
    {
        "target_id": 98092666,
        "target_screen_name": "sergiocagol",
        "source_id": 223439979
    },
    {
        "target_id": 10735852,
        "target_screen_name": "macteo",
        "source_id": 223439979
    },
    {
        "target_id": 109550596,
        "target_screen_name": "iamgalba",
        "source_id": 223439979
    },
    {
        "target_id": 1291422799,
        "target_screen_name": "talentgardenen",
        "source_id": 223439979
    },
    {
        "target_id": 1163231527,
        "target_screen_name": "TEDxTrento",
        "source_id": 223439979
    },
    {
        "target_id": 14523150,
        "target_screen_name": "davidedattoli",
        "source_id": 223439979
    },
    {
        "target_id": 17336393,
        "target_screen_name": "gabricocek",
        "source_id": 223439979
    },
    {
        "target_id": 1059407979219427328,
        "target_screen_name": "TnDigit",
        "source_id": 223439979
    },
    {
        "target_id": 46088486,
        "target_screen_name": "darnocks",
        "source_id": 223439979
    },
    {
        "target_id": 765548,
        "target_screen_name": "hmason",
        "source_id": 223439979
    },
    {
        "target_id": 307410719,
        "target_screen_name": "carlocaprini",
        "source_id": 223439979
    },
    {
        "target_id": 1055438473,
        "target_screen_name": "bddorj",
        "source_id": 223439979
    },
    {
        "target_id": 931497057034080256,
        "target_screen_name": "project_cpn",
        "source_id": 223439979
    },
    {
        "target_id": 25990086,
        "target_screen_name": "mediamocracy",
        "source_id": 223439979
    },
    {
        "target_id": 136256258,
        "target_screen_name": "openlivinglabs",
        "source_id": 223439979
    },
    {
        "target_id": 22628899,
        "target_screen_name": "tmforumorg",
        "source_id": 223439979
    },
    {
        "target_id": 828610901666365440,
        "target_screen_name": "SyncCityIoT",
        "source_id": 223439979
    },
    {
        "target_id": 798126196567457793,
        "target_screen_name": "martel_mchiara",
        "source_id": 223439979
    },
    {
        "target_id": 22635867,
        "target_screen_name": "molli75",
        "source_id": 223439979
    },
    {
        "target_id": 1090251725590663169,
        "target_screen_name": "WeNetProject",
        "source_id": 223439979
    },
    {
        "target_id": 1084761037222670336,
        "target_screen_name": "STavonatti",
        "source_id": 223439979
    },
    {
        "target_id": 3253909977,
        "target_screen_name": "ele_aste",
        "source_id": 223439979
    },
    {
        "target_id": 6967672,
        "target_screen_name": "andersn64",
        "source_id": 223439979
    },
    {
        "target_id": 79730794,
        "target_screen_name": "MarcoTurchini",
        "source_id": 223439979
    },
    {
        "target_id": 27832245,
        "target_screen_name": "dancit",
        "source_id": 223439979
    },
    {
        "target_id": 340282732,
        "target_screen_name": "RaftMat",
        "source_id": 223439979
    },
    {
        "target_id": 753110521730199554,
        "target_screen_name": "eh_azimi",
        "source_id": 223439979
    },
    {
        "target_id": 60851479,
        "target_screen_name": "luciamazzoni",
        "source_id": 223439979
    },
    {
        "target_id": 226961418,
        "target_screen_name": "SilvanaSanfeliu",
        "source_id": 223439979
    },
    {
        "target_id": 1057682298294943744,
        "target_screen_name": "Snap4City",
        "source_id": 223439979
    },
    {
        "target_id": 1062704978891075585,
        "target_screen_name": "tsslsse",
        "source_id": 223439979
    },
    {
        "target_id": 1269644016,
        "target_screen_name": "DatiTrentinoit",
        "source_id": 223439979
    },
    {
        "target_id": 564573799,
        "target_screen_name": "investtrentino",
        "source_id": 223439979
    },
    {
        "target_id": 89651197,
        "target_screen_name": "Aisling_Irwin",
        "source_id": 223439979
    },
    {
        "target_id": 910541935244431362,
        "target_screen_name": "gpierre_ur1",
        "source_id": 223439979
    },
    {
        "target_id": 193301414,
        "target_screen_name": "EUScienceInnov",
        "source_id": 223439979
    },
    {
        "target_id": 467551928,
        "target_screen_name": "ERC_Research",
        "source_id": 223439979
    },
    {
        "target_id": 330860720,
        "target_screen_name": "EITeu",
        "source_id": 223439979
    },
    {
        "target_id": 278506592,
        "target_screen_name": "MSCActions",
        "source_id": 223439979
    },
    {
        "target_id": 144821473,
        "target_screen_name": "taslab",
        "source_id": 223439979
    },
    {
        "target_id": 124874351,
        "target_screen_name": "VisitTrentino",
        "source_id": 223439979
    },
    {
        "target_id": 735482417763389440,
        "target_screen_name": "trentosmart",
        "source_id": 223439979
    },
    {
        "target_id": 721353577831206912,
        "target_screen_name": "5gempower",
        "source_id": 223439979
    },
    {
        "target_id": 162365356,
        "target_screen_name": "lucapieraccini",
        "source_id": 223439979
    },
    {
        "target_id": 4846474297,
        "target_screen_name": "irisa_lab",
        "source_id": 223439979
    },
    {
        "target_id": 1028846656374988801,
        "target_screen_name": "decenterproject",
        "source_id": 223439979
    },
    {
        "target_id": 106364904,
        "target_screen_name": "CORDIS_EU",
        "source_id": 223439979
    },
    {
        "target_id": 936202105697783808,
        "target_screen_name": "MozhdeFarhadi",
        "source_id": 223439979
    },
    {
        "target_id": 984729270294646785,
        "target_screen_name": "innaxis_aero",
        "source_id": 223439979
    },
    {
        "target_id": 14130914,
        "target_screen_name": "ddalledo",
        "source_id": 223439979
    },
    {
        "target_id": 1479712676,
        "target_screen_name": "brandalesis",
        "source_id": 223439979
    },
    {
        "target_id": 159061069,
        "target_screen_name": "WeAreAlgonomy",
        "source_id": 223439979
    },
    {
        "target_id": 45213880,
        "target_screen_name": "KatinkaSchaaf",
        "source_id": 223439979
    },
    {
        "target_id": 15039499,
        "target_screen_name": "fspagnoli",
        "source_id": 223439979
    },
    {
        "target_id": 4524025395,
        "target_screen_name": "IoT_Forum",
        "source_id": 223439979
    },
    {
        "target_id": 359085773,
        "target_screen_name": "SamanthaBaita",
        "source_id": 223439979
    },
    {
        "target_id": 76982240,
        "target_screen_name": "Lebowskiana",
        "source_id": 223439979
    },
    {
        "target_id": 515654938,
        "target_screen_name": "luca_barso",
        "source_id": 223439979
    },
    {
        "target_id": 604686251,
        "target_screen_name": "bigdive_eu",
        "source_id": 223439979
    },
    {
        "target_id": 901763676,
        "target_screen_name": "laprofrinaldi",
        "source_id": 223439979
    },
    {
        "target_id": 14397047,
        "target_screen_name": "dagoneye",
        "source_id": 223439979
    },
    {
        "target_id": 34906475,
        "target_screen_name": "AleLoRusso",
        "source_id": 223439979
    },
    {
        "target_id": 7559072,
        "target_screen_name": "marcomb",
        "source_id": 223439979
    },
    {
        "target_id": 4527320117,
        "target_screen_name": "beppeaceto",
        "source_id": 223439979
    },
    {
        "target_id": 1342092410,
        "target_screen_name": "Industriofund",
        "source_id": 223439979
    },
    {
        "target_id": 406530098,
        "target_screen_name": "ChiaraMaule",
        "source_id": 223439979
    },
    {
        "target_id": 3314963469,
        "target_screen_name": "dmedialab",
        "source_id": 223439979
    },
    {
        "target_id": 47699270,
        "target_screen_name": "lilloraffa",
        "source_id": 223439979
    },
    {
        "target_id": 803655634545741824,
        "target_screen_name": "DataDrivenInnov",
        "source_id": 223439979
    },
    {
        "target_id": 4914940289,
        "target_screen_name": "FInterop",
        "source_id": 223439979
    },
    {
        "target_id": 53349828,
        "target_screen_name": "mchgli",
        "source_id": 223439979
    },
    {
        "target_id": 725422427665215488,
        "target_screen_name": "cioUniTrento",
        "source_id": 223439979
    },
    {
        "target_id": 14858300,
        "target_screen_name": "diegopia",
        "source_id": 223439979
    },
    {
        "target_id": 598662680,
        "target_screen_name": "Mattia_Antonini",
        "source_id": 223439979
    },
    {
        "target_id": 15249151,
        "target_screen_name": "maciejkranz",
        "source_id": 223439979
    },
    {
        "target_id": 208895287,
        "target_screen_name": "RobertoMinerva",
        "source_id": 223439979
    },
    {
        "target_id": 221366410,
        "target_screen_name": "nicolopomini",
        "source_id": 223439979
    },
    {
        "target_id": 789206992795598848,
        "target_screen_name": "ahumey",
        "source_id": 223439979
    },
    {
        "target_id": 877221943300300800,
        "target_screen_name": "WeObserveEU",
        "source_id": 223439979
    },
    {
        "target_id": 2383503595,
        "target_screen_name": "blueupbeacons",
        "source_id": 223439979
    },
    {
        "target_id": 770574232329785344,
        "target_screen_name": "Osiris_Interreg",
        "source_id": 223439979
    },
    {
        "target_id": 137337075,
        "target_screen_name": "Piersoft",
        "source_id": 223439979
    },
    {
        "target_id": 3601749196,
        "target_screen_name": "LucaCapra69",
        "source_id": 223439979
    },
    {
        "target_id": 934394366474489858,
        "target_screen_name": "ISENSE_GROUP",
        "source_id": 223439979
    },
    {
        "target_id": 928699702647906305,
        "target_screen_name": "krommyda_maria",
        "source_id": 223439979
    },
    {
        "target_id": 894057794,
        "target_screen_name": "Strategy_Gal",
        "source_id": 223439979
    },
    {
        "target_id": 53611450,
        "target_screen_name": "hubtrentino",
        "source_id": 223439979
    },
    {
        "target_id": 836942734598492160,
        "target_screen_name": "marta_casarotto",
        "source_id": 223439979
    },
    {
        "target_id": 134050862,
        "target_screen_name": "chicco785",
        "source_id": 223439979
    },
    {
        "target_id": 831805647993917442,
        "target_screen_name": "DITASproject",
        "source_id": 223439979
    },
    {
        "target_id": 852530934,
        "target_screen_name": "MartaCalderaro",
        "source_id": 223439979
    },
    {
        "target_id": 636139110,
        "target_screen_name": "GiovannaDiTroia",
        "source_id": 223439979
    },
    {
        "target_id": 99959376,
        "target_screen_name": "Micio1970",
        "source_id": 223439979
    },
    {
        "target_id": 722151877,
        "target_screen_name": "macolap",
        "source_id": 223439979
    },
    {
        "target_id": 910160649824677888,
        "target_screen_name": "thefogguru",
        "source_id": 223439979
    },
    {
        "target_id": 1731304340,
        "target_screen_name": "Martel_Innovate",
        "source_id": 223439979
    },
    {
        "target_id": 824627061478322176,
        "target_screen_name": "eu_graph",
        "source_id": 223439979
    },
    {
        "target_id": 831445828149661697,
        "target_screen_name": "DataPitchEU",
        "source_id": 223439979
    },
    {
        "target_id": 3749685377,
        "target_screen_name": "FreyIza",
        "source_id": 223439979
    },
    {
        "target_id": 1098452624,
        "target_screen_name": "st3phenmcK",
        "source_id": 223439979
    },
    {
        "target_id": 104562738,
        "target_screen_name": "adelynzhou",
        "source_id": 223439979
    },
    {
        "target_id": 3238616285,
        "target_screen_name": "thinkinsidecorp",
        "source_id": 223439979
    },
    {
        "target_id": 297933855,
        "target_screen_name": "CarrCommsLtd",
        "source_id": 223439979
    },
    {
        "target_id": 43101964,
        "target_screen_name": "hfarmspa",
        "source_id": 223439979
    },
    {
        "target_id": 579812426,
        "target_screen_name": "fioronigiacomo",
        "source_id": 223439979
    },
    {
        "target_id": 3044619729,
        "target_screen_name": "smrtcmmnt",
        "source_id": 223439979
    },
    {
        "target_id": 19281320,
        "target_screen_name": "zaccog",
        "source_id": 223439979
    },
    {
        "target_id": 280110533,
        "target_screen_name": "PeterBaeck",
        "source_id": 223439979
    },
    {
        "target_id": 15227849,
        "target_screen_name": "semil",
        "source_id": 223439979
    },
    {
        "target_id": 827446273754198016,
        "target_screen_name": "IoF2020",
        "source_id": 223439979
    },
    {
        "target_id": 1510204819,
        "target_screen_name": "FETFX_EU",
        "source_id": 223439979
    },
    {
        "target_id": 16743617,
        "target_screen_name": "SAPCXDataCloud",
        "source_id": 223439979
    },
    {
        "target_id": 729589027326791680,
        "target_screen_name": "HIT_trentino",
        "source_id": 223439979
    },
    {
        "target_id": 37683656,
        "target_screen_name": "stefano_venturi",
        "source_id": 223439979
    },
    {
        "target_id": 571985466,
        "target_screen_name": "claudio_bassoli",
        "source_id": 223439979
    },
    {
        "target_id": 491477916,
        "target_screen_name": "SolaFabio",
        "source_id": 223439979
    },
    {
        "target_id": 111060272,
        "target_screen_name": "thinkmariya",
        "source_id": 223439979
    },
    {
        "target_id": 418868960,
        "target_screen_name": "john_magan",
        "source_id": 223439979
    },
    {
        "target_id": 842056847716691968,
        "target_screen_name": "city_welcom",
        "source_id": 223439979
    },
    {
        "target_id": 2873548169,
        "target_screen_name": "arossiale",
        "source_id": 223439979
    },
    {
        "target_id": 104282672,
        "target_screen_name": "MarcRennard",
        "source_id": 223439979
    },
    {
        "target_id": 772751482999414784,
        "target_screen_name": "UnBias_algos",
        "source_id": 223439979
    },
    {
        "target_id": 1379662802,
        "target_screen_name": "HorizonEU",
        "source_id": 223439979
    },
    {
        "target_id": 16492108,
        "target_screen_name": "dder",
        "source_id": 223439979
    },
    {
        "target_id": 425633801,
        "target_screen_name": "IdairaRobayna",
        "source_id": 223439979
    },
    {
        "target_id": 2714046698,
        "target_screen_name": "TenguPaaS",
        "source_id": 223439979
    },
    {
        "target_id": 20305301,
        "target_screen_name": "laepple",
        "source_id": 223439979
    },
    {
        "target_id": 801017191579656192,
        "target_screen_name": "ICT_FLAME",
        "source_id": 223439979
    },
    {
        "target_id": 28526621,
        "target_screen_name": "SaraBrodersen",
        "source_id": 223439979
    },
    {
        "target_id": 131351259,
        "target_screen_name": "michelenati",
        "source_id": 223439979
    },
    {
        "target_id": 694884939607646209,
        "target_screen_name": "IoT_EPI",
        "source_id": 223439979
    },
    {
        "target_id": 47370898,
        "target_screen_name": "cohendjcohen",
        "source_id": 223439979
    },
    {
        "target_id": 209104350,
        "target_screen_name": "OlivettiOnline",
        "source_id": 223439979
    },
    {
        "target_id": 15955731,
        "target_screen_name": "cbock",
        "source_id": 223439979
    },
    {
        "target_id": 2251577246,
        "target_screen_name": "FreedomeVPN",
        "source_id": 223439979
    },
    {
        "target_id": 2351874108,
        "target_screen_name": "NGI4eu",
        "source_id": 223439979
    },
    {
        "target_id": 63451547,
        "target_screen_name": "marcoagosti",
        "source_id": 223439979
    },
    {
        "target_id": 17379987,
        "target_screen_name": "GoAcoustic",
        "source_id": 223439979
    },
    {
        "target_id": 2897460873,
        "target_screen_name": "ambroma74",
        "source_id": 223439979
    },
    {
        "target_id": 604457411,
        "target_screen_name": "comune_velletri",
        "source_id": 223439979
    },
    {
        "target_id": 136770972,
        "target_screen_name": "luca_masi",
        "source_id": 223439979
    },
    {
        "target_id": 793515799268954117,
        "target_screen_name": "Fet2Rin",
        "source_id": 223439979
    },
    {
        "target_id": 553729228,
        "target_screen_name": "alex_pentland",
        "source_id": 223439979
    },
    {
        "target_id": 3802194221,
        "target_screen_name": "i3_FBK",
        "source_id": 223439979
    },
    {
        "target_id": 248596750,
        "target_screen_name": "fabienastic",
        "source_id": 223439979
    },
    {
        "target_id": 20571756,
        "target_screen_name": "satyanadella",
        "source_id": 223439979
    },
    {
        "target_id": 399307197,
        "target_screen_name": "Catapult_UK",
        "source_id": 223439979
    },
    {
        "target_id": 66998204,
        "target_screen_name": "innovateuk",
        "source_id": 223439979
    },
    {
        "target_id": 4256439658,
        "target_screen_name": "fiesta_iot",
        "source_id": 223439979
    },
    {
        "target_id": 203332110,
        "target_screen_name": "worldbankdata",
        "source_id": 223439979
    },
    {
        "target_id": 81656841,
        "target_screen_name": "EnricoVerga",
        "source_id": 223439979
    },
    {
        "target_id": 3291204419,
        "target_screen_name": "Triangulum_EU",
        "source_id": 223439979
    },
    {
        "target_id": 8439372,
        "target_screen_name": "earsc",
        "source_id": 223439979
    },
    {
        "target_id": 875678749,
        "target_screen_name": "MKutvonen",
        "source_id": 223439979
    },
    {
        "target_id": 701742141639434240,
        "target_screen_name": "INTER_IoT",
        "source_id": 223439979
    },
    {
        "target_id": 5387212,
        "target_screen_name": "schingler",
        "source_id": 223439979
    },
    {
        "target_id": 463937151,
        "target_screen_name": "VanyaNikova",
        "source_id": 223439979
    },
    {
        "target_id": 456095421,
        "target_screen_name": "postma_rob",
        "source_id": 223439979
    },
    {
        "target_id": 2547694218,
        "target_screen_name": "ICTproposerEU",
        "source_id": 223439979
    },
    {
        "target_id": 19586808,
        "target_screen_name": "aBandCalledPaul",
        "source_id": 223439979
    },
    {
        "target_id": 772786326122991616,
        "target_screen_name": "SCENT_EU",
        "source_id": 223439979
    },
    {
        "target_id": 534255106,
        "target_screen_name": "ODIHQ",
        "source_id": 223439979
    },
    {
        "target_id": 256210681,
        "target_screen_name": "EU_Startups",
        "source_id": 223439979
    },
    {
        "target_id": 7162442,
        "target_screen_name": "aabella",
        "source_id": 223439979
    },
    {
        "target_id": 1548402403,
        "target_screen_name": "lornagoulden",
        "source_id": 223439979
    },
    {
        "target_id": 424898211,
        "target_screen_name": "EFFRA_Live",
        "source_id": 223439979
    },
    {
        "target_id": 47999622,
        "target_screen_name": "ResearchEurope",
        "source_id": 223439979
    },
    {
        "target_id": 2745508573,
        "target_screen_name": "ieeebigdata",
        "source_id": 223439979
    },
    {
        "target_id": 77205186,
        "target_screen_name": "jamesturner247",
        "source_id": 223439979
    },
    {
        "target_id": 2306228096,
        "target_screen_name": "Boomtown",
        "source_id": 223439979
    },
    {
        "target_id": 84175601,
        "target_screen_name": "marcgiorgini",
        "source_id": 223439979
    },
    {
        "target_id": 1315071697,
        "target_screen_name": "DataSmartCities",
        "source_id": 223439979
    },
    {
        "target_id": 369365481,
        "target_screen_name": "IceSte86",
        "source_id": 223439979
    },
    {
        "target_id": 3333153436,
        "target_screen_name": "leanplc",
        "source_id": 223439979
    },
    {
        "target_id": 2898806649,
        "target_screen_name": "DECCELERATOR",
        "source_id": 223439979
    },
    {
        "target_id": 107527616,
        "target_screen_name": "elepetrucciano",
        "source_id": 223439979
    },
    {
        "target_id": 705000752633286656,
        "target_screen_name": "AllianzPartners",
        "source_id": 223439979
    },
    {
        "target_id": 4901473949,
        "target_screen_name": "EO4InnovationEU",
        "source_id": 223439979
    },
    {
        "target_id": 261254083,
        "target_screen_name": "adianselmo",
        "source_id": 223439979
    },
    {
        "target_id": 2223451512,
        "target_screen_name": "xdotai",
        "source_id": 223439979
    },
    {
        "target_id": 2485285236,
        "target_screen_name": "finodexproject",
        "source_id": 223439979
    },
    {
        "target_id": 3995155588,
        "target_screen_name": "Kissmy_bike",
        "source_id": 223439979
    },
    {
        "target_id": 374143531,
        "target_screen_name": "DarioMazzella",
        "source_id": 223439979
    },
    {
        "target_id": 707185129744113665,
        "target_screen_name": "symbiote_h2020",
        "source_id": 223439979
    },
    {
        "target_id": 2972047805,
        "target_screen_name": "OrganiCity_eu",
        "source_id": 223439979
    },
    {
        "target_id": 487534443,
        "target_screen_name": "MariaBoychenko",
        "source_id": 223439979
    },
    {
        "target_id": 2885923163,
        "target_screen_name": "Lombardi_Lucy",
        "source_id": 223439979
    },
    {
        "target_id": 33669105,
        "target_screen_name": "JosephSteinberg",
        "source_id": 223439979
    },
    {
        "target_id": 4234699311,
        "target_screen_name": "agile_iot",
        "source_id": 223439979
    },
    {
        "target_id": 5723512,
        "target_screen_name": "stefanobernardi",
        "source_id": 223439979
    },
    {
        "target_id": 356164932,
        "target_screen_name": "FBK_research",
        "source_id": 223439979
    },
    {
        "target_id": 120116275,
        "target_screen_name": "rafweverbergh",
        "source_id": 223439979
    },
    {
        "target_id": 15930061,
        "target_screen_name": "HilzFuld",
        "source_id": 223439979
    },
    {
        "target_id": 17776351,
        "target_screen_name": "mart_museum",
        "source_id": 223439979
    },
    {
        "target_id": 285428413,
        "target_screen_name": "jessfraz",
        "source_id": 223439979
    },
    {
        "target_id": 318332175,
        "target_screen_name": "eurohumph",
        "source_id": 223439979
    },
    {
        "target_id": 112683173,
        "target_screen_name": "duplikey",
        "source_id": 223439979
    },
    {
        "target_id": 4480456761,
        "target_screen_name": "retail_reply",
        "source_id": 223439979
    },
    {
        "target_id": 299685250,
        "target_screen_name": "silgasa",
        "source_id": 223439979
    },
    {
        "target_id": 1842817177,
        "target_screen_name": "MoniqueCalisti",
        "source_id": 223439979
    },
    {
        "target_id": 196690048,
        "target_screen_name": "TIMnewsroom",
        "source_id": 223439979
    },
    {
        "target_id": 196690048,
        "target_screen_name": "TIMnewsroom",
        "source_id": 223439979
    },
    {
        "target_id": 4897577411,
        "target_screen_name": "_ChantalGarnier",
        "source_id": 223439979
    },
    {
        "target_id": 15339875,
        "target_screen_name": "stefpos",
        "source_id": 223439979
    },
    {
        "target_id": 38254620,
        "target_screen_name": "giorgialupi",
        "source_id": 223439979
    },
    {
        "target_id": 192954268,
        "target_screen_name": "opentopic",
        "source_id": 223439979
    },
    {
        "target_id": 2307675307,
        "target_screen_name": "TamaraMcCleary",
        "source_id": 223439979
    },
    {
        "target_id": 17752870,
        "target_screen_name": "s_a_brooks",
        "source_id": 223439979
    },
    {
        "target_id": 34372776,
        "target_screen_name": "ncracchi",
        "source_id": 223439979
    },
    {
        "target_id": 2863843925,
        "target_screen_name": "guarinotn",
        "source_id": 223439979
    },
    {
        "target_id": 19389800,
        "target_screen_name": "VickiTurk",
        "source_id": 223439979
    },
    {
        "target_id": 147470258,
        "target_screen_name": "samlightstone",
        "source_id": 223439979
    },
    {
        "target_id": 3189139057,
        "target_screen_name": "LeanXcale",
        "source_id": 223439979
    },
    {
        "target_id": 2648509428,
        "target_screen_name": "Mira_Analytics",
        "source_id": 223439979
    },
    {
        "target_id": 1565724332,
        "target_screen_name": "girard_yann",
        "source_id": 223439979
    },
    {
        "target_id": 621515931,
        "target_screen_name": "huydanle",
        "source_id": 223439979
    },
    {
        "target_id": 928406365,
        "target_screen_name": "Radianse",
        "source_id": 223439979
    },
    {
        "target_id": 437417872,
        "target_screen_name": "HetIsEric",
        "source_id": 223439979
    },
    {
        "target_id": 3255870885,
        "target_screen_name": "analyticschap",
        "source_id": 223439979
    },
    {
        "target_id": 80278539,
        "target_screen_name": "giorpomo",
        "source_id": 223439979
    },
    {
        "target_id": 58021052,
        "target_screen_name": "fede_menna",
        "source_id": 223439979
    },
    {
        "target_id": 58021052,
        "target_screen_name": "fede_menna",
        "source_id": 223439979
    },
    {
        "target_id": 460051524,
        "target_screen_name": "PartechPartners",
        "source_id": 223439979
    },
    {
        "target_id": 5813712,
        "target_screen_name": "antirez",
        "source_id": 223439979
    },
    {
        "target_id": 162006707,
        "target_screen_name": "Sofi_Real",
        "source_id": 223439979
    },
    {
        "target_id": 1024244078,
        "target_screen_name": "EvanSinar",
        "source_id": 223439979
    },
    {
        "target_id": 225560234,
        "target_screen_name": "rblocke",
        "source_id": 223439979
    },
    {
        "target_id": 1201313390,
        "target_screen_name": "sunshine_EU",
        "source_id": 223439979
    },
    {
        "target_id": 3351574797,
        "target_screen_name": "MrNoSQL",
        "source_id": 223439979
    },
    {
        "target_id": 19669170,
        "target_screen_name": "RayHartjen",
        "source_id": 223439979
    },
    {
        "target_id": 562088327,
        "target_screen_name": "FaberAntonelli",
        "source_id": 223439979
    },
    {
        "target_id": 19007524,
        "target_screen_name": "risnewsinsights",
        "source_id": 223439979
    },
    {
        "target_id": 17395556,
        "target_screen_name": "JeffFromm",
        "source_id": 223439979
    },
    {
        "target_id": 1894231788,
        "target_screen_name": "datasociety",
        "source_id": 223439979
    },
    {
        "target_id": 76966092,
        "target_screen_name": "johnrampton",
        "source_id": 223439979
    },
    {
        "target_id": 529562963,
        "target_screen_name": "OpenContent_IT",
        "source_id": 223439979
    },
    {
        "target_id": 2811492056,
        "target_screen_name": "DigitalChampITA",
        "source_id": 223439979
    },
    {
        "target_id": 2815408383,
        "target_screen_name": "martin_steinman",
        "source_id": 223439979
    },
    {
        "target_id": 13260592,
        "target_screen_name": "fpav",
        "source_id": 223439979
    },
    {
        "target_id": 49133000,
        "target_screen_name": "custoz",
        "source_id": 223439979
    },
    {
        "target_id": 363375942,
        "target_screen_name": "insideBigData",
        "source_id": 223439979
    },
    {
        "target_id": 3172769218,
        "target_screen_name": "atoka_io",
        "source_id": 223439979
    },
    {
        "target_id": 1856980754,
        "target_screen_name": "CanvasVC",
        "source_id": 223439979
    },
    {
        "target_id": 2237231593,
        "target_screen_name": "dicoweb",
        "source_id": 223439979
    },
    {
        "target_id": 195760172,
        "target_screen_name": "ExasolAG",
        "source_id": 223439979
    },
    {
        "target_id": 2152942698,
        "target_screen_name": "LucaPezzolla1",
        "source_id": 223439979
    },
    {
        "target_id": 25296032,
        "target_screen_name": "ScalaInc",
        "source_id": 223439979
    },
    {
        "target_id": 33700317,
        "target_screen_name": "dom1789",
        "source_id": 223439979
    },
    {
        "target_id": 260672276,
        "target_screen_name": "ekimetrics",
        "source_id": 223439979
    },
    {
        "target_id": 321524268,
        "target_screen_name": "Aditya_Vijay_A",
        "source_id": 223439979
    },
    {
        "target_id": 2210171,
        "target_screen_name": "MichaelvanLaar",
        "source_id": 223439979
    },
    {
        "target_id": 2313928178,
        "target_screen_name": "mariopaterlini",
        "source_id": 223439979
    },
    {
        "target_id": 23516942,
        "target_screen_name": "gfulgoni",
        "source_id": 223439979
    },
    {
        "target_id": 267469345,
        "target_screen_name": "FIWARE",
        "source_id": 223439979
    },
    {
        "target_id": 18994444,
        "target_screen_name": "IBM",
        "source_id": 223439979
    },
    {
        "target_id": 2829894761,
        "target_screen_name": "welcomestartup",
        "source_id": 223439979
    },
    {
        "target_id": 2469573385,
        "target_screen_name": "CitObsBCN",
        "source_id": 223439979
    },
    {
        "target_id": 218419895,
        "target_screen_name": "Kesslers_Ltd",
        "source_id": 223439979
    },
    {
        "target_id": 2413022749,
        "target_screen_name": "AyleeNielsen",
        "source_id": 223439979
    },
    {
        "target_id": 63241507,
        "target_screen_name": "aonetti",
        "source_id": 223439979
    },
    {
        "target_id": 2318670234,
        "target_screen_name": "FGraphitech",
        "source_id": 223439979
    },
    {
        "target_id": 633,
        "target_screen_name": "zephoria",
        "source_id": 223439979
    },
    {
        "target_id": 52059265,
        "target_screen_name": "_giohappy_",
        "source_id": 223439979
    },
    {
        "target_id": 60918418,
        "target_screen_name": "cdippolito",
        "source_id": 223439979
    },
    {
        "target_id": 296320946,
        "target_screen_name": "SAPTradeGeek",
        "source_id": 223439979
    },
    {
        "target_id": 1392130746,
        "target_screen_name": "fer_napolitano",
        "source_id": 223439979
    },
    {
        "target_id": 17508918,
        "target_screen_name": "renaudvisage",
        "source_id": 223439979
    },
    {
        "target_id": 2868176019,
        "target_screen_name": "Ben_Fournier_",
        "source_id": 223439979
    },
    {
        "target_id": 20536157,
        "target_screen_name": "Google",
        "source_id": 223439979
    },
    {
        "target_id": 1149663985,
        "target_screen_name": "QualcommVenture",
        "source_id": 223439979
    },
    {
        "target_id": 17238288,
        "target_screen_name": "retexperience",
        "source_id": 223439979
    },
    {
        "target_id": 537101136,
        "target_screen_name": "26alex30",
        "source_id": 223439979
    },
    {
        "target_id": 2312332872,
        "target_screen_name": "HaggerstonTimes",
        "source_id": 223439979
    },
    {
        "target_id": 822928860,
        "target_screen_name": "CreativeRing",
        "source_id": 223439979
    },
    {
        "target_id": 49413866,
        "target_screen_name": "randal_olson",
        "source_id": 223439979
    },
    {
        "target_id": 113130846,
        "target_screen_name": "ycombinator",
        "source_id": 223439979
    },
    {
        "target_id": 7095,
        "target_screen_name": "Cookie",
        "source_id": 223439979
    },
    {
        "target_id": 5943622,
        "target_screen_name": "pmarca",
        "source_id": 223439979
    },
    {
        "target_id": 494357346,
        "target_screen_name": "startup_italia",
        "source_id": 223439979
    },
    {
        "target_id": 2758681690,
        "target_screen_name": "WearableGuru",
        "source_id": 223439979
    },
    {
        "target_id": 2876435657,
        "target_screen_name": "MODIS_Unit",
        "source_id": 223439979
    },
    {
        "target_id": 3313569215,
        "target_screen_name": "ReckonPoint",
        "source_id": 223439979
    },
    {
        "target_id": 10427102,
        "target_screen_name": "richardbliss",
        "source_id": 223439979
    },
    {
        "target_id": 125400714,
        "target_screen_name": "fabiomoioli",
        "source_id": 223439979
    },
    {
        "target_id": 3009556327,
        "target_screen_name": "BereAlexandre",
        "source_id": 223439979
    },
    {
        "target_id": 6795682,
        "target_screen_name": "fbp",
        "source_id": 223439979
    },
    {
        "target_id": 1582703370,
        "target_screen_name": "GourdonRetail",
        "source_id": 223439979
    },
    {
        "target_id": 2797602696,
        "target_screen_name": "EXAGolo",
        "source_id": 223439979
    },
    {
        "target_id": 17455384,
        "target_screen_name": "Coppo",
        "source_id": 223439979
    },
    {
        "target_id": 1448330136,
        "target_screen_name": "nestholma",
        "source_id": 223439979
    },
    {
        "target_id": 17617546,
        "target_screen_name": "topij",
        "source_id": 223439979
    },
    {
        "target_id": 1447417104,
        "target_screen_name": "CivisAnalytics",
        "source_id": 223439979
    },
    {
        "target_id": 27907602,
        "target_screen_name": "noahkeil09",
        "source_id": 223439979
    },
    {
        "target_id": 20167623,
        "target_screen_name": "kdnuggets",
        "source_id": 223439979
    },
    {
        "target_id": 731853602,
        "target_screen_name": "SAPStartups",
        "source_id": 223439979
    },
    {
        "target_id": 1155320395,
        "target_screen_name": "Cloudiusss",
        "source_id": 223439979
    },
    {
        "target_id": 123708821,
        "target_screen_name": "cakemark",
        "source_id": 223439979
    },
    {
        "target_id": 14235711,
        "target_screen_name": "Wittkamper",
        "source_id": 223439979
    },
    {
        "target_id": 2743028023,
        "target_screen_name": "Unacast",
        "source_id": 223439979
    },
    {
        "target_id": 2860570191,
        "target_screen_name": "celect",
        "source_id": 223439979
    },
    {
        "target_id": 488802976,
        "target_screen_name": "ItaBusiness",
        "source_id": 223439979
    },
    {
        "target_id": 2431896534,
        "target_screen_name": "GruppoVege",
        "source_id": 223439979
    },
    {
        "target_id": 299364430,
        "target_screen_name": "Everette",
        "source_id": 223439979
    },
    {
        "target_id": 2532942559,
        "target_screen_name": "wtvox",
        "source_id": 223439979
    },
    {
        "target_id": 29368419,
        "target_screen_name": "OpenMove",
        "source_id": 223439979
    },
    {
        "target_id": 81902684,
        "target_screen_name": "antoniomaresca",
        "source_id": 223439979
    },
    {
        "target_id": 199049790,
        "target_screen_name": "AcumenMR",
        "source_id": 223439979
    },
    {
        "target_id": 703119944,
        "target_screen_name": "FreshOOHMedia",
        "source_id": 223439979
    },
    {
        "target_id": 15330301,
        "target_screen_name": "ericcolson",
        "source_id": 223439979
    },
    {
        "target_id": 1324180910,
        "target_screen_name": "mcsdinamica",
        "source_id": 223439979
    },
    {
        "target_id": 536596389,
        "target_screen_name": "ElvisKoci",
        "source_id": 223439979
    },
    {
        "target_id": 377297496,
        "target_screen_name": "suvilavinto",
        "source_id": 223439979
    },
    {
        "target_id": 307753350,
        "target_screen_name": "TestingSaaS",
        "source_id": 223439979
    },
    {
        "target_id": 288500051,
        "target_screen_name": "cldrcommunity",
        "source_id": 223439979
    },
    {
        "target_id": 1145369852,
        "target_screen_name": "hugoschuitema",
        "source_id": 223439979
    },
    {
        "target_id": 62058481,
        "target_screen_name": "MassimoGiordani",
        "source_id": 223439979
    },
    {
        "target_id": 204297410,
        "target_screen_name": "_krisjack",
        "source_id": 223439979
    },
    {
        "target_id": 2591467812,
        "target_screen_name": "gsantambrogio1",
        "source_id": 223439979
    },
    {
        "target_id": 17392100,
        "target_screen_name": "PlugandPlayTC",
        "source_id": 223439979
    },
    {
        "target_id": 2558988457,
        "target_screen_name": "technews_today",
        "source_id": 223439979
    },
    {
        "target_id": 16361040,
        "target_screen_name": "noelito",
        "source_id": 223439979
    },
    {
        "target_id": 889099657,
        "target_screen_name": "Analytics_Sam",
        "source_id": 223439979
    },
    {
        "target_id": 72741763,
        "target_screen_name": "Envirosell",
        "source_id": 223439979
    },
    {
        "target_id": 2487960978,
        "target_screen_name": "releaseman",
        "source_id": 223439979
    },
    {
        "target_id": 478440185,
        "target_screen_name": "esalvad",
        "source_id": 223439979
    },
    {
        "target_id": 3096335597,
        "target_screen_name": "dandelionapi",
        "source_id": 223439979
    },
    {
        "target_id": 526561639,
        "target_screen_name": "pitchrs",
        "source_id": 223439979
    },
    {
        "target_id": 221460294,
        "target_screen_name": "vivian__zhang",
        "source_id": 223439979
    },
    {
        "target_id": 369334970,
        "target_screen_name": "AlleyWatch",
        "source_id": 223439979
    },
    {
        "target_id": 99086125,
        "target_screen_name": "thomaswalle",
        "source_id": 223439979
    },
    {
        "target_id": 1571068567,
        "target_screen_name": "tech_eu",
        "source_id": 223439979
    },
    {
        "target_id": 17350542,
        "target_screen_name": "Informatica",
        "source_id": 223439979
    },
    {
        "target_id": 320241050,
        "target_screen_name": "KarolPokojowczy",
        "source_id": 223439979
    },
    {
        "target_id": 2397497832,
        "target_screen_name": "EngineeringSpa",
        "source_id": 223439979
    },
    {
        "target_id": 3024824936,
        "target_screen_name": "launchmonkey",
        "source_id": 223439979
    },
    {
        "target_id": 2520999920,
        "target_screen_name": "NYCDataSci",
        "source_id": 223439979
    },
    {
        "target_id": 861765444,
        "target_screen_name": "BIdotcom",
        "source_id": 223439979
    },
    {
        "target_id": 10273462,
        "target_screen_name": "jmcquivey",
        "source_id": 223439979
    },
    {
        "target_id": 3147285911,
        "target_screen_name": "51DegreesData",
        "source_id": 223439979
    },
    {
        "target_id": 248868797,
        "target_screen_name": "iAmJoshHunt",
        "source_id": 223439979
    },
    {
        "target_id": 1702148870,
        "target_screen_name": "Iamherox",
        "source_id": 223439979
    },
    {
        "target_id": 3062151,
        "target_screen_name": "BrettHenry",
        "source_id": 223439979
    },
    {
        "target_id": 351578264,
        "target_screen_name": "Guru_Frandsen",
        "source_id": 223439979
    },
    {
        "target_id": 562891302,
        "target_screen_name": "Alvamark_1926",
        "source_id": 223439979
    },
    {
        "target_id": 159421391,
        "target_screen_name": "esse_ti",
        "source_id": 223439979
    },
    {
        "target_id": 516369603,
        "target_screen_name": "BoltAcc",
        "source_id": 223439979
    },
    {
        "target_id": 211605302,
        "target_screen_name": "fbelloni",
        "source_id": 223439979
    },
    {
        "target_id": 3190140759,
        "target_screen_name": "iNSPIREcn",
        "source_id": 223439979
    },
    {
        "target_id": 134724878,
        "target_screen_name": "clagiuliano",
        "source_id": 223439979
    },
    {
        "target_id": 1329224334,
        "target_screen_name": "ChrisAn31320018",
        "source_id": 223439979
    },
    {
        "target_id": 193462243,
        "target_screen_name": "hzynczak",
        "source_id": 223439979
    },
    {
        "target_id": 12705022,
        "target_screen_name": "pppaolo",
        "source_id": 223439979
    },
    {
        "target_id": 379924298,
        "target_screen_name": "OscardiMontigny",
        "source_id": 223439979
    },
    {
        "target_id": 225749784,
        "target_screen_name": "mat_masse",
        "source_id": 223439979
    },
    {
        "target_id": 25007589,
        "target_screen_name": "PlasticBankPHI",
        "source_id": 223439979
    },
    {
        "target_id": 16273972,
        "target_screen_name": "Loyalty360",
        "source_id": 223439979
    },
    {
        "target_id": 72982024,
        "target_screen_name": "gapingvoid",
        "source_id": 223439979
    },
    {
        "target_id": 14137033,
        "target_screen_name": "nimkar",
        "source_id": 223439979
    },
    {
        "target_id": 15120222,
        "target_screen_name": "iHiD",
        "source_id": 223439979
    },
    {
        "target_id": 137455381,
        "target_screen_name": "DavidKatzPB",
        "source_id": 223439979
    },
    {
        "target_id": 97487983,
        "target_screen_name": "jraitamaa",
        "source_id": 223439979
    },
    {
        "target_id": 305277457,
        "target_screen_name": "Sharezi",
        "source_id": 223439979
    },
    {
        "target_id": 2336967348,
        "target_screen_name": "Pushmote",
        "source_id": 223439979
    },
    {
        "target_id": 2751674648,
        "target_screen_name": "CreatiFi_FI",
        "source_id": 223439979
    },
    {
        "target_id": 444940567,
        "target_screen_name": "garybizzo",
        "source_id": 223439979
    },
    {
        "target_id": 108112690,
        "target_screen_name": "florianguillaum",
        "source_id": 223439979
    },
    {
        "target_id": 2888882327,
        "target_screen_name": "Data88Smart",
        "source_id": 223439979
    },
    {
        "target_id": 125723797,
        "target_screen_name": "curiouspub",
        "source_id": 223439979
    },
    {
        "target_id": 312901735,
        "target_screen_name": "RmiVIDAL",
        "source_id": 223439979
    },
    {
        "target_id": 85001062,
        "target_screen_name": "drbrandonyoung",
        "source_id": 223439979
    },
    {
        "target_id": 555031989,
        "target_screen_name": "Ronald_vanLoon",
        "source_id": 223439979
    },
    {
        "target_id": 511740616,
        "target_screen_name": "biconnections",
        "source_id": 223439979
    },
    {
        "target_id": 95648100,
        "target_screen_name": "ramongaspar",
        "source_id": 223439979
    },
    {
        "target_id": 2303133834,
        "target_screen_name": "headcountguru",
        "source_id": 223439979
    },
    {
        "target_id": 61891251,
        "target_screen_name": "mikeginnyc",
        "source_id": 223439979
    },
    {
        "target_id": 267254947,
        "target_screen_name": "AndreasRades",
        "source_id": 223439979
    },
    {
        "target_id": 69748123,
        "target_screen_name": "heyAdamCrouch",
        "source_id": 223439979
    },
    {
        "target_id": 51882318,
        "target_screen_name": "UXemploys",
        "source_id": 223439979
    },
    {
        "target_id": 3021237551,
        "target_screen_name": "niftytech_news",
        "source_id": 223439979
    },
    {
        "target_id": 1560608858,
        "target_screen_name": "COMPOSE_Project",
        "source_id": 223439979
    },
    {
        "target_id": 317005063,
        "target_screen_name": "AlexanderD_Beck",
        "source_id": 223439979
    },
    {
        "target_id": 1617314359,
        "target_screen_name": "JoeFindsTalent",
        "source_id": 223439979
    },
    {
        "target_id": 15695513,
        "target_screen_name": "hughballou",
        "source_id": 223439979
    },
    {
        "target_id": 21991908,
        "target_screen_name": "TheDataAgent",
        "source_id": 223439979
    },
    {
        "target_id": 1121028973,
        "target_screen_name": "Jeff88Ho",
        "source_id": 223439979
    },
    {
        "target_id": 2987295922,
        "target_screen_name": "wonderflow",
        "source_id": 223439979
    },
    {
        "target_id": 186642255,
        "target_screen_name": "smartwhere",
        "source_id": 223439979
    },
    {
        "target_id": 1497848766,
        "target_screen_name": "200crowd",
        "source_id": 223439979
    },
    {
        "target_id": 14426771,
        "target_screen_name": "SeanEllis",
        "source_id": 223439979
    },
    {
        "target_id": 3060042483,
        "target_screen_name": "SuccessRetweets",
        "source_id": 223439979
    },
    {
        "target_id": 488802767,
        "target_screen_name": "InnoEnergyEU",
        "source_id": 223439979
    },
    {
        "target_id": 2248542728,
        "target_screen_name": "IA4SI",
        "source_id": 223439979
    },
    {
        "target_id": 39540686,
        "target_screen_name": "Engagement360",
        "source_id": 223439979
    },
    {
        "target_id": 2896911596,
        "target_screen_name": "CatchTalkLaunch",
        "source_id": 223439979
    },
    {
        "target_id": 131500972,
        "target_screen_name": "HuffPostContrib",
        "source_id": 223439979
    },
    {
        "target_id": 1735241,
        "target_screen_name": "RiCHi",
        "source_id": 223439979
    },
    {
        "target_id": 2680135712,
        "target_screen_name": "startuplister",
        "source_id": 223439979
    },
    {
        "target_id": 45235247,
        "target_screen_name": "vallver",
        "source_id": 223439979
    },
    {
        "target_id": 17354555,
        "target_screen_name": "emilio__ferrara",
        "source_id": 223439979
    },
    {
        "target_id": 2361547466,
        "target_screen_name": "OnionIoT",
        "source_id": 223439979
    },
    {
        "target_id": 46632251,
        "target_screen_name": "AspireSystems",
        "source_id": 223439979
    },
    {
        "target_id": 112700518,
        "target_screen_name": "bt_global",
        "source_id": 223439979
    },
    {
        "target_id": 1547845368,
        "target_screen_name": "nextome",
        "source_id": 223439979
    },
    {
        "target_id": 16468227,
        "target_screen_name": "Campaignmag",
        "source_id": 223439979
    },
    {
        "target_id": 192065852,
        "target_screen_name": "SmarterRetailer",
        "source_id": 223439979
    },
    {
        "target_id": 7712452,
        "target_screen_name": "forrester",
        "source_id": 223439979
    },
    {
        "target_id": 8457092,
        "target_screen_name": "Deloitte",
        "source_id": 223439979
    },
    {
        "target_id": 28363090,
        "target_screen_name": "OracleRetail",
        "source_id": 223439979
    },
    {
        "target_id": 14885549,
        "target_screen_name": "ForbesTech",
        "source_id": 223439979
    },
    {
        "target_id": 106377188,
        "target_screen_name": "Stylus_LIVE",
        "source_id": 223439979
    },
    {
        "target_id": 1951748148,
        "target_screen_name": "movintracks",
        "source_id": 223439979
    },
    {
        "target_id": 2313056851,
        "target_screen_name": "beaconomist",
        "source_id": 223439979
    },
    {
        "target_id": 551269336,
        "target_screen_name": "RadiusNetworks",
        "source_id": 223439979
    },
    {
        "target_id": 1957364688,
        "target_screen_name": "ibeaconsblog",
        "source_id": 223439979
    },
    {
        "target_id": 747782522,
        "target_screen_name": "Estimote",
        "source_id": 223439979
    },
    {
        "target_id": 595945891,
        "target_screen_name": "beaconpowered",
        "source_id": 223439979
    },
    {
        "target_id": 2291263734,
        "target_screen_name": "inbeacons",
        "source_id": 223439979
    },
    {
        "target_id": 1670120228,
        "target_screen_name": "kontakt_io",
        "source_id": 223439979
    },
    {
        "target_id": 465608753,
        "target_screen_name": "GeLoInc",
        "source_id": 223439979
    },
    {
        "target_id": 51976275,
        "target_screen_name": "tinkztweetz",
        "source_id": 223439979
    },
    {
        "target_id": 189554835,
        "target_screen_name": "JeffDeGraff",
        "source_id": 223439979
    },
    {
        "target_id": 81947660,
        "target_screen_name": "SanFranciscoVC",
        "source_id": 223439979
    },
    {
        "target_id": 2187345613,
        "target_screen_name": "DDiochnos",
        "source_id": 223439979
    },
    {
        "target_id": 218980363,
        "target_screen_name": "thorstenkramp",
        "source_id": 223439979
    },
    {
        "target_id": 153966123,
        "target_screen_name": "CynthiaLIVE",
        "source_id": 223439979
    },
    {
        "target_id": 92490693,
        "target_screen_name": "effemax",
        "source_id": 223439979
    },
    {
        "target_id": 23418251,
        "target_screen_name": "nivox",
        "source_id": 223439979
    },
    {
        "target_id": 1244399556,
        "target_screen_name": "_nommon",
        "source_id": 223439979
    },
    {
        "target_id": 28514542,
        "target_screen_name": "RMagnifico",
        "source_id": 223439979
    },
    {
        "target_id": 311722396,
        "target_screen_name": "CooperPickett",
        "source_id": 223439979
    },
    {
        "target_id": 1959460147,
        "target_screen_name": "aislelabs",
        "source_id": 223439979
    },
    {
        "target_id": 10944002,
        "target_screen_name": "leweb",
        "source_id": 223439979
    },
    {
        "target_id": 2597780983,
        "target_screen_name": "unboundglobal",
        "source_id": 223439979
    },
    {
        "target_id": 246175187,
        "target_screen_name": "MBP1961",
        "source_id": 223439979
    },
    {
        "target_id": 2317661245,
        "target_screen_name": "IEEEIoT",
        "source_id": 223439979
    },
    {
        "target_id": 2499289070,
        "target_screen_name": "Googleorg",
        "source_id": 223439979
    },
    {
        "target_id": 17214580,
        "target_screen_name": "RiccardoLuna",
        "source_id": 223439979
    },
    {
        "target_id": 74426272,
        "target_screen_name": "AccentureActive",
        "source_id": 223439979
    },
    {
        "target_id": 539946626,
        "target_screen_name": "SpazioDati",
        "source_id": 223439979
    },
    {
        "target_id": 19588475,
        "target_screen_name": "timwcap",
        "source_id": 223439979
    },
    {
        "target_id": 26911403,
        "target_screen_name": "finSMEs",
        "source_id": 223439979
    },
    {
        "target_id": 2437493161,
        "target_screen_name": "IEEESmartCities",
        "source_id": 223439979
    },
    {
        "target_id": 76117579,
        "target_screen_name": "SAP",
        "source_id": 223439979
    },
    {
        "target_id": 1307183304,
        "target_screen_name": "MtlLab",
        "source_id": 223439979
    },
    {
        "target_id": 183749519,
        "target_screen_name": "paulg",
        "source_id": 223439979
    },
    {
        "target_id": 974100978,
        "target_screen_name": "smartcampus_lab",
        "source_id": 223439979
    },
    {
        "target_id": 131882442,
        "target_screen_name": "innovlab",
        "source_id": 223439979
    },
    {
        "target_id": 834998532,
        "target_screen_name": "SKIL_Lab",
        "source_id": 223439979
    },
    {
        "target_id": 1190059830,
        "target_screen_name": "fatherio",
        "source_id": 223439979
    },
    {
        "target_id": 1723526154,
        "target_screen_name": "retailerIN",
        "source_id": 223439979
    },
    {
        "target_id": 267939430,
        "target_screen_name": "KPMG",
        "source_id": 223439979
    },
    {
        "target_id": 1929789500,
        "target_screen_name": "UniTrento_DISI",
        "source_id": 223439979
    },
    {
        "target_id": 140407690,
        "target_screen_name": "EAI_Social",
        "source_id": 223439979
    },
    {
        "target_id": 2383715653,
        "target_screen_name": "ICT_2B",
        "source_id": 223439979
    },
    {
        "target_id": 360562509,
        "target_screen_name": "giaffred",
        "source_id": 223439979
    },
    {
        "target_id": 557549422,
        "target_screen_name": "JegLev",
        "source_id": 223439979
    },
    {
        "target_id": 327184784,
        "target_screen_name": "Prism",
        "source_id": 223439979
    },
    {
        "target_id": 34026146,
        "target_screen_name": "RetailNext",
        "source_id": 223439979
    },
    {
        "target_id": 275700771,
        "target_screen_name": "walkbase",
        "source_id": 223439979
    },
    {
        "target_id": 2238908498,
        "target_screen_name": "Josh_Jaco",
        "source_id": 223439979
    },
    {
        "target_id": 22028833,
        "target_screen_name": "msretail",
        "source_id": 223439979
    },
    {
        "target_id": 418034772,
        "target_screen_name": "ninjamarketing",
        "source_id": 223439979
    },
    {
        "target_id": 14109159,
        "target_screen_name": "Capgemini",
        "source_id": 223439979
    },
    {
        "target_id": 2208027565,
        "target_screen_name": "ProductHunt",
        "source_id": 223439979
    },
    {
        "target_id": 30912050,
        "target_screen_name": "herbsorensen",
        "source_id": 223439979
    },
    {
        "target_id": 8453452,
        "target_screen_name": "GuyKawasaki",
        "source_id": 223439979
    },
    {
        "target_id": 2313778956,
        "target_screen_name": "iLocateProject",
        "source_id": 223439979
    },
    {
        "target_id": 33838201,
        "target_screen_name": "GoogleAI",
        "source_id": 223439979
    },
    {
        "target_id": 50634671,
        "target_screen_name": "frnwtr",
        "source_id": 223439979
    },
    {
        "target_id": 75079616,
        "target_screen_name": "IFTTT",
        "source_id": 223439979
    },
    {
        "target_id": 832366926,
        "target_screen_name": "QuuppaTech",
        "source_id": 223439979
    },
    {
        "target_id": 410696446,
        "target_screen_name": "AleZorer",
        "source_id": 223439979
    },
    {
        "target_id": 161235815,
        "target_screen_name": "graffiti2000",
        "source_id": 223439979
    },
    {
        "target_id": 816653,
        "target_screen_name": "TechCrunch",
        "source_id": 223439979
    },
    {
        "target_id": 15231287,
        "target_screen_name": "Gartner_inc",
        "source_id": 223439979
    },
    {
        "target_id": 13666,
        "target_screen_name": "mikebutcher",
        "source_id": 223439979
    },
    {
        "target_id": 29735775,
        "target_screen_name": "IBMWatson",
        "source_id": 223439979
    },
    {
        "target_id": 2599679101,
        "target_screen_name": "IMPACT_acc",
        "source_id": 223439979
    },
    {
        "target_id": 204750852,
        "target_screen_name": "DataNativesCon",
        "source_id": 223439979
    },
    {
        "target_id": 16319797,
        "target_screen_name": "IBMResearch",
        "source_id": 223439979
    },
    {
        "target_id": 10243852,
        "target_screen_name": "mlanzil",
        "source_id": 223439979
    },
    {
        "target_id": 600880141,
        "target_screen_name": "createnet",
        "source_id": 223439979
    },
    {
        "target_id": 369463619,
        "target_screen_name": "SiamoSoci",
        "source_id": 223439979
    },
    {
        "target_id": 14193192,
        "target_screen_name": "nisselson",
        "source_id": 223439979
    },
    {
        "target_id": 606160025,
        "target_screen_name": "TnSviluppo",
        "source_id": 223439979
    },
    {
        "target_id": 295633020,
        "target_screen_name": "EIT_Digital",
        "source_id": 223439979
    },
    {
        "target_id": 1076495262,
        "target_screen_name": "trilogis",
        "source_id": 223439979
    },
    {
        "target_id": 17227954,
        "target_screen_name": "paololombardi",
        "source_id": 223439979
    },
    {
        "target_id": 14305589,
        "target_screen_name": "bindik",
        "source_id": 223439979
    },
    {
        "target_id": 2617063015,
        "target_screen_name": "tapoi_cloud",
        "source_id": 223439979
    },
    {
        "target_id": 1303571503,
        "target_screen_name": "DataEcoEU",
        "source_id": 223439979
    },
    {
        "target_id": 1446296545,
        "target_screen_name": "DSI4EU",
        "source_id": 223439979
    },
    {
        "target_id": 292324718,
        "target_screen_name": "DEDAGROUP_ICT",
        "source_id": 223439979
    },
    {
        "target_id": 1412867028,
        "target_screen_name": "Mancino_F",
        "source_id": 223439979
    },
    {
        "target_id": 2613580795,
        "target_screen_name": "vbarchetti",
        "source_id": 223439979
    },
    {
        "target_id": 267283568,
        "target_screen_name": "IBMData",
        "source_id": 223439979
    },
    {
        "target_id": 16017475,
        "target_screen_name": "NateSilver538",
        "source_id": 223439979
    },
    {
        "target_id": 543598566,
        "target_screen_name": "AccentureAI",
        "source_id": 223439979
    },
    {
        "target_id": 51263711,
        "target_screen_name": "googleanalytics",
        "source_id": 223439979
    },
    {
        "target_id": 1089817363,
        "target_screen_name": "TechPeaks",
        "source_id": 223439979
    },
    {
        "target_id": 1734596533,
        "target_screen_name": "SmartSocietyFP7",
        "source_id": 223439979
    },
    {
        "target_id": 1446281586,
        "target_screen_name": "DanieleMiorandi",
        "source_id": 223439979
    },
    {
        "target_id": 17093617,
        "target_screen_name": "hootsuite",
        "source_id": 223439979
    },
    {
        "target_id": 54875219,
        "target_screen_name": "lpannese",
        "source_id": 223439979
    },
    {
        "target_id": 67670571,
        "target_screen_name": "ditag01",
        "source_id": 223439979
    },
    {
        "target_id": 1109264149,
        "target_screen_name": "AlbertoR77",
        "source_id": 223439979
    },
    {
        "target_id": 28479684,
        "target_screen_name": "deadroxy",
        "source_id": 223439979
    },
    {
        "target_id": 106904609,
        "target_screen_name": "frestylnews",
        "source_id": 223439979
    },
    {
        "target_id": 458731801,
        "target_screen_name": "IGPDecaux",
        "source_id": 223439979
    },
    {
        "target_id": 475041580,
        "target_screen_name": "sqrmap",
        "source_id": 223439979
    }
]